{"bronze":{"1":265392,"2":315446,"3":1219037,"image":"https://mrapi.org/assets/ranks/bronze.png"},"silver":{"1":213815,"2":245566,"3":286621,"image":"https://mrapi.org/assets/ranks/silver.png"},"gold":{"1":158610,"2":189183,"3":273162,"image":"https://mrapi.org/assets/ranks/gold.png"},"platinum":{"1":76581,"2":114853,"3":186652,"image":"https://mrapi.org/assets/ranks/platinum.png"},"diamond":{"1":29966,"2":45679,"3":79549,"image":"https://mrapi.org/assets/ranks/diamond.png"},"grandmaster":{"1":11007,"2":18490,"3":44182,"image":"https://mrapi.org/assets/ranks/grandmaster.png"},"celestial":{"1":1711,"2":4019,"3":11868,"image":"https://mrapi.org/assets/ranks/celestial.png"},"eternity":{"total":1571,"image":"https://mrapi.org/assets/ranks/eternity.png"},"one_above_all":{"total":559,"image":"https://mrapi.org/assets/ranks/one_above_all.png"}}