[{"rank":1,"player_name":"Eyton","rank_name":"One Above All","score":5147,"matches":55,"player_id":302325187},{"rank":2,"player_name":"FatalFrr","rank_name":"Eternity","score":5119,"matches":91,"player_id":1034553050},{"rank":3,"player_name":"Angadxo","rank_name":"Eternity","score":5114,"matches":87,"player_id":1545202546},{"rank":4,"player_name":"Opact","rank_name":"Celestial 1","score":5068,"matches":56,"player_id":127340649},{"rank":5,"player_name":"LewNotSerious","rank_name":"Celestial 1","score":5030,"matches":166,"player_id":871116073},{"rank":6,"player_name":"JoeeOT","rank_name":"Celestial 1","score":5025,"matches":64,"player_id":1451983189},{"rank":7,"player_name":"Jabagas","rank_name":"Celestial 1","score":5021,"matches":60,"player_id":308295252},{"rank":8,"player_name":"Raw.Doggin","rank_name":"Celestial 1","score":5003,"matches":151,"player_id":443587228},{"rank":9,"player_name":"toughertuba617","rank_name":"Celestial 1","score":5000,"matches":67,"player_id":1828500506},{"rank":10,"player_name":"Jurassic1n","rank_name":"Celestial 2","score":4997,"matches":185,"player_id":811336683},{"rank":11,"player_name":"NiceSpy","rank_name":"Celestial 1","score":4981,"matches":93,"player_id":630265256},{"rank":12,"player_name":"Kryw","rank_name":"Celestial 2","score":4981,"matches":59,"player_id":799467694},{"rank":13,"player_name":"Kjimi","rank_name":"Celestial 2","score":4967,"matches":188,"player_id":1095935421},{"rank":14,"player_name":"Sacrement","rank_name":"Celestial 2","score":4925,"matches":53,"player_id":1132516621},{"rank":15,"player_name":"ronaljajaxd","rank_name":"Celestial 2","score":4921,"matches":296,"player_id":1079052458},{"rank":16,"player_name":"huskeh","rank_name":"Celestial 2","score":4913,"matches":61,"player_id":127409006},{"rank":17,"player_name":"brosky.","rank_name":"Celestial 2","score":4911,"matches":57,"player_id":956136197},{"rank":18,"player_name":"IceColdCombos","rank_name":"Celestial 2","score":4896,"matches":74,"player_id":467067160},{"rank":19,"player_name":"SigmaMale","rank_name":"Celestial 2","score":4874,"matches":80,"player_id":1691803983},{"rank":20,"player_name":"JetStream","rank_name":"Celestial 3","score":4867,"matches":252,"player_id":337343511},{"rank":21,"player_name":"ᵈᵛˡ","rank_name":"Celestial 3","score":4857,"matches":57,"player_id":943871262},{"rank":22,"player_name":"WOW R34LLY K1D","rank_name":"Celestial 3","score":4851,"matches":94,"player_id":282055330},{"rank":23,"player_name":"FarmingSoulz","rank_name":"Celestial 3","score":4845,"matches":129,"player_id":2004919368},{"rank":24,"player_name":"ACDC IRONMAN","rank_name":"Celestial 3","score":4839,"matches":148,"player_id":1923935995},{"rank":25,"player_name":"WeAreJay","rank_name":"Celestial 3","score":4839,"matches":147,"player_id":1955483280},{"rank":26,"player_name":"Altair2","rank_name":"Celestial 3","score":4835,"matches":51,"player_id":1361039522},{"rank":27,"player_name":"lnsomniac","rank_name":"Celestial 3","score":4832,"matches":126,"player_id":152126847},{"rank":28,"player_name":"freeze fv","rank_name":"Celestial 3","score":4830,"matches":132,"player_id":398602598},{"rank":29,"player_name":"mrstealurgoats","rank_name":"Celestial 3","score":4827,"matches":94,"player_id":1178550403},{"rank":30,"player_name":"elad_ow","rank_name":"Celestial 3","score":4824,"matches":54,"player_id":225017213},{"rank":31,"player_name":"Yos2","rank_name":"Celestial 3","score":4824,"matches":55,"player_id":699156902},{"rank":32,"player_name":"Kihoon","rank_name":"Celestial 3","score":4821,"matches":55,"player_id":715202770},{"rank":33,"player_name":"ChooChooWho","rank_name":"Celestial 3","score":4819,"matches":56,"player_id":1005681285},{"rank":34,"player_name":"Darkin774","rank_name":"Celestial 3","score":4818,"matches":85,"player_id":859099484},{"rank":35,"player_name":"Kabzon","rank_name":"Celestial 3","score":4817,"matches":59,"player_id":1882463553},{"rank":36,"player_name":"SoydraxGM","rank_name":"Celestial 3","score":4816,"matches":79,"player_id":328922856},{"rank":37,"player_name":"HENTAILOVER091","rank_name":"Celestial 3","score":4815,"matches":176,"player_id":202071438},{"rank":38,"player_name":"Sebastien Harp","rank_name":"Celestial 3","score":4814,"matches":143,"player_id":1851954773},{"rank":39,"player_name":"KirikoFeetLovr","rank_name":"Celestial 3","score":4812,"matches":72,"player_id":338463065},{"rank":40,"player_name":"Acherons","rank_name":"Celestial 3","score":4812,"matches":60,"player_id":759096770},{"rank":41,"player_name":"Ariancool","rank_name":"Celestial 3","score":4809,"matches":128,"player_id":337158930},{"rank":42,"player_name":"TanklessHERO","rank_name":"Celestial 3","score":4809,"matches":51,"player_id":1733381314},{"rank":43,"player_name":"Ghangi ツ","rank_name":"Celestial 3","score":4808,"matches":86,"player_id":713567147},{"rank":44,"player_name":"WarMachine1112","rank_name":"Celestial 3","score":4805,"matches":138,"player_id":798520727},{"rank":45,"player_name":"GenuineBaller","rank_name":"Celestial 3","score":4801,"matches":82,"player_id":836799232},{"rank":46,"player_name":"TimFromOBlock","rank_name":"Celestial 3","score":4801,"matches":66,"player_id":551539962},{"rank":47,"player_name":"trickstus","rank_name":"Celestial 3","score":4800,"matches":98,"player_id":303575040},{"rank":48,"player_name":"rnzu","rank_name":"Celestial 3","score":4800,"matches":133,"player_id":1925915241},{"rank":49,"player_name":"Benjer8","rank_name":"Celestial 3","score":4800,"matches":56,"player_id":934961262},{"rank":50,"player_name":"Arcneex","rank_name":"Celestial 3","score":4797,"matches":75,"player_id":1093582387},{"rank":51,"player_name":"Sirequentin","rank_name":"Celestial 3","score":4792,"matches":60,"player_id":2043724940},{"rank":52,"player_name":"BLACKEDWHORE","rank_name":"Grandmaster 1","score":4776,"matches":70,"player_id":114739356},{"rank":53,"player_name":"GoyPlayingMR","rank_name":"Grandmaster 1","score":4775,"matches":67,"player_id":1136410458},{"rank":54,"player_name":"Heliocrash","rank_name":"Grandmaster 1","score":4773,"matches":203,"player_id":1040995990},{"rank":55,"player_name":"TriXa_Bly4T","rank_name":"Grandmaster 1","score":4763,"matches":130,"player_id":293688015},{"rank":56,"player_name":"Top2chainz","rank_name":"Grandmaster 1","score":4758,"matches":102,"player_id":253754305},{"rank":57,"player_name":"Reapssb201","rank_name":"Grandmaster 1","score":4755,"matches":160,"player_id":1502862542},{"rank":58,"player_name":"Tbucs","rank_name":"Grandmaster 1","score":4750,"matches":57,"player_id":1150276670},{"rank":59,"player_name":"KnF Turbo","rank_name":"Grandmaster 1","score":4749,"matches":166,"player_id":1532817429},{"rank":60,"player_name":"LEEEGEENDARYYY","rank_name":"Grandmaster 1","score":4746,"matches":62,"player_id":1306026005},{"rank":61,"player_name":"zorkkana","rank_name":"Grandmaster 1","score":4745,"matches":78,"player_id":315982958},{"rank":62,"player_name":".XR","rank_name":"Grandmaster 1","score":4744,"matches":62,"player_id":2090586925},{"rank":63,"player_name":"JuC3","rank_name":"Grandmaster 1","score":4743,"matches":84,"player_id":1276068088},{"rank":64,"player_name":"30secondtomars","rank_name":"Grandmaster 1","score":4740,"matches":305,"player_id":1498715725},{"rank":65,"player_name":"VivaLaTaper","rank_name":"Grandmaster 1","score":4736,"matches":78,"player_id":427352189},{"rank":66,"player_name":"OmObtekar","rank_name":"Grandmaster 1","score":4736,"matches":233,"player_id":714976131},{"rank":67,"player_name":"NearN1","rank_name":"Grandmaster 1","score":4734,"matches":51,"player_id":665268357},{"rank":68,"player_name":"Not ZeroOo","rank_name":"Grandmaster 1","score":4725,"matches":338,"player_id":1392725437},{"rank":69,"player_name":"vgchamp1","rank_name":"Grandmaster 1","score":4725,"matches":66,"player_id":1856573843},{"rank":70,"player_name":"RonySize","rank_name":"Grandmaster 1","score":4723,"matches":63,"player_id":1144886809},{"rank":71,"player_name":"Nirusen","rank_name":"Grandmaster 1","score":4721,"matches":183,"player_id":1951665918},{"rank":72,"player_name":"Gabara04","rank_name":"Grandmaster 1","score":4717,"matches":79,"player_id":1826139401},{"rank":73,"player_name":"LimoJen","rank_name":"Grandmaster 1","score":4716,"matches":65,"player_id":246186474},{"rank":74,"player_name":"SinFulHawk TTV","rank_name":"Grandmaster 1","score":4714,"matches":61,"player_id":145206127},{"rank":75,"player_name":"Larch ツ","rank_name":"Grandmaster 1","score":4714,"matches":77,"player_id":1903647169},{"rank":76,"player_name":"grgrgr","rank_name":"Grandmaster 1","score":4713,"matches":127,"player_id":2064681561},{"rank":77,"player_name":"JB76","rank_name":"Grandmaster 1","score":4710,"matches":76,"player_id":1965579012},{"rank":78,"player_name":"Kopgalos","rank_name":"Grandmaster 1","score":4706,"matches":61,"player_id":486262220},{"rank":79,"player_name":"MeleèGod","rank_name":"Grandmaster 1","score":4706,"matches":72,"player_id":1713313823},{"rank":80,"player_name":"smurfetico1337","rank_name":"Grandmaster 1","score":4704,"matches":190,"player_id":608448028},{"rank":81,"player_name":"Lahlid","rank_name":"Grandmaster 1","score":4704,"matches":241,"player_id":1340595809},{"rank":82,"player_name":"pommchamp","rank_name":"Grandmaster 1","score":4699,"matches":53,"player_id":1318678338},{"rank":83,"player_name":"Wulfan","rank_name":"Grandmaster 2","score":4697,"matches":76,"player_id":334415147},{"rank":84,"player_name":"sakkexwx","rank_name":"Grandmaster 1","score":4694,"matches":68,"player_id":1463060271},{"rank":85,"player_name":"Canadian Hero","rank_name":"Grandmaster 1","score":4693,"matches":55,"player_id":48895174},{"rank":86,"player_name":"hedlund1","rank_name":"Grandmaster 2","score":4691,"matches":79,"player_id":204790184},{"rank":87,"player_name":"Brzaa","rank_name":"Grandmaster 1","score":4688,"matches":71,"player_id":149407922},{"rank":88,"player_name":"CarryPoliPoli","rank_name":"Grandmaster 1","score":4687,"matches":89,"player_id":2146104753},{"rank":89,"player_name":"Exted","rank_name":"Grandmaster 2","score":4684,"matches":108,"player_id":42795918},{"rank":90,"player_name":"Wazakazawa","rank_name":"Grandmaster 1","score":4681,"matches":77,"player_id":1666482526},{"rank":91,"player_name":"Brzav","rank_name":"Grandmaster 1","score":4678,"matches":219,"player_id":159398466},{"rank":92,"player_name":"Chatakuri","rank_name":"Grandmaster 1","score":4677,"matches":52,"player_id":448657365},{"rank":93,"player_name":"iRodor1","rank_name":"Grandmaster 1","score":4675,"matches":544,"player_id":683742412},{"rank":94,"player_name":"Bearking","rank_name":"Grandmaster 2","score":4671,"matches":63,"player_id":1103196529},{"rank":95,"player_name":"darty deedsu","rank_name":"Grandmaster 2","score":4669,"matches":142,"player_id":2015318732},{"rank":96,"player_name":"Penisaurous","rank_name":"Grandmaster 2","score":4667,"matches":87,"player_id":36896737},{"rank":97,"player_name":"Anomaly2k","rank_name":"Grandmaster 2","score":4650,"matches":235,"player_id":722323897},{"rank":98,"player_name":"lmkcardin","rank_name":"Grandmaster 2","score":4645,"matches":187,"player_id":398930874},{"rank":99,"player_name":"ZanCryw","rank_name":"Grandmaster 2","score":4637,"matches":77,"player_id":415301695},{"rank":100,"player_name":"BWC_Gamer","rank_name":"Grandmaster 2","score":4633,"matches":153,"player_id":982956627},{"rank":101,"player_name":"Vance MK-II","rank_name":"Grandmaster 2","score":4629,"matches":74,"player_id":1269309807},{"rank":102,"player_name":"Once1776","rank_name":"Grandmaster 2","score":4625,"matches":85,"player_id":1589693563},{"rank":103,"player_name":"GamerGoose389","rank_name":"Grandmaster 2","score":4623,"matches":71,"player_id":1828282287},{"rank":104,"player_name":"zVon","rank_name":"Grandmaster 2","score":4621,"matches":72,"player_id":1681652032},{"rank":105,"player_name":"ThorTheyThem","rank_name":"Grandmaster 2","score":4620,"matches":75,"player_id":359893639},{"rank":106,"player_name":"GabeOW","rank_name":"Grandmaster 2","score":4620,"matches":65,"player_id":1262765690},{"rank":107,"player_name":"SharpBats","rank_name":"Grandmaster 2","score":4619,"matches":55,"player_id":1175393930},{"rank":108,"player_name":"Iron man Thor","rank_name":"Grandmaster 2","score":4617,"matches":102,"player_id":1710469657},{"rank":109,"player_name":"SLQB","rank_name":"Grandmaster 2","score":4615,"matches":127,"player_id":179686275},{"rank":110,"player_name":"I_am_GrOm","rank_name":"Grandmaster 2","score":4612,"matches":66,"player_id":1044781273},{"rank":111,"player_name":"Seifcc","rank_name":"Grandmaster 2","score":4610,"matches":88,"player_id":181010191},{"rank":112,"player_name":"ZAGIAS","rank_name":"Grandmaster 2","score":4609,"matches":108,"player_id":1177047576},{"rank":113,"player_name":"2stronkk","rank_name":"Grandmaster 2","score":4609,"matches":59,"player_id":889214906},{"rank":114,"player_name":"Kazum4","rank_name":"Grandmaster 2","score":4609,"matches":57,"player_id":1183185379},{"rank":115,"player_name":"SK No Mercy","rank_name":"Grandmaster 2","score":4608,"matches":140,"player_id":1205154026},{"rank":116,"player_name":"ovP5H7o","rank_name":"Grandmaster 2","score":4608,"matches":72,"player_id":1719224893},{"rank":117,"player_name":"MonkeyManReal1","rank_name":"Grandmaster 2","score":4605,"matches":252,"player_id":491390324},{"rank":118,"player_name":"E777","rank_name":"Grandmaster 2","score":4605,"matches":268,"player_id":73258670},{"rank":119,"player_name":"Pilon Végétal","rank_name":"Grandmaster 2","score":4605,"matches":234,"player_id":710513701},{"rank":120,"player_name":"HUNK_NA","rank_name":"Grandmaster 2","score":4604,"matches":64,"player_id":344256680},{"rank":121,"player_name":"keimbel","rank_name":"Grandmaster 2","score":4603,"matches":138,"player_id":753358225},{"rank":122,"player_name":"Slickius","rank_name":"Grandmaster 2","score":4601,"matches":90,"player_id":891819797},{"rank":123,"player_name":"Luccama","rank_name":"Grandmaster 3","score":4598,"matches":65,"player_id":2000970531},{"rank":124,"player_name":"Kasdeyaz","rank_name":"Grandmaster 3","score":4595,"matches":115,"player_id":1656198118},{"rank":125,"player_name":"TTV 7marmo","rank_name":"Grandmaster 3","score":4595,"matches":70,"player_id":1151574743},{"rank":126,"player_name":"exe","rank_name":"Grandmaster 2","score":4595,"matches":56,"player_id":1610234753},{"rank":127,"player_name":"XLspirit","rank_name":"Grandmaster 2","score":4592,"matches":100,"player_id":629598654},{"rank":128,"player_name":"VerZonic","rank_name":"Grandmaster 2","score":4589,"matches":60,"player_id":2099611309},{"rank":129,"player_name":"Dark1y","rank_name":"Grandmaster 2","score":4588,"matches":74,"player_id":250594593},{"rank":130,"player_name":"WanderingSmurf","rank_name":"Grandmaster 2","score":4588,"matches":52,"player_id":1543914894},{"rank":131,"player_name":"1900Rugrat","rank_name":"Grandmaster 2","score":4585,"matches":199,"player_id":1182320177},{"rank":132,"player_name":"KyleNewin","rank_name":"Grandmaster 2","score":4585,"matches":109,"player_id":1605883434},{"rank":133,"player_name":"Surf_4","rank_name":"Grandmaster 2","score":4585,"matches":57,"player_id":1441407937},{"rank":134,"player_name":"Fitrah","rank_name":"Grandmaster 3","score":4581,"matches":79,"player_id":319231020},{"rank":135,"player_name":"WmbaZ4Q","rank_name":"Grandmaster 2","score":4581,"matches":84,"player_id":869560721},{"rank":136,"player_name":"satsu...","rank_name":"Grandmaster 2","score":4581,"matches":99,"player_id":1242346537},{"rank":137,"player_name":"AneFlank14","rank_name":"Grandmaster 3","score":4581,"matches":53,"player_id":1076520302},{"rank":138,"player_name":"IGOR05_99","rank_name":"Grandmaster 2","score":4575,"matches":136,"player_id":994884427},{"rank":139,"player_name":"Alvl80Paladin","rank_name":"Grandmaster 2","score":4572,"matches":71,"player_id":1948999721},{"rank":140,"player_name":"Joggekr","rank_name":"Grandmaster 3","score":4567,"matches":162,"player_id":1997248388},{"rank":141,"player_name":"PrinceXmatta","rank_name":"Grandmaster 3","score":4567,"matches":51,"player_id":659879975},{"rank":142,"player_name":"Funky Monke","rank_name":"Grandmaster 3","score":4563,"matches":56,"player_id":1080045133},{"rank":143,"player_name":"Durandal","rank_name":"Grandmaster 3","score":4561,"matches":82,"player_id":1201772306},{"rank":144,"player_name":"neverta","rank_name":"Grandmaster 3","score":4559,"matches":97,"player_id":1454578545},{"rank":145,"player_name":"Georgatron","rank_name":"Grandmaster 3","score":4558,"matches":90,"player_id":1903187778},{"rank":146,"player_name":"King GreyTTV","rank_name":"Grandmaster 3","score":4556,"matches":89,"player_id":1931285741},{"rank":147,"player_name":"ScarecrowwFTP","rank_name":"Grandmaster 3","score":4555,"matches":60,"player_id":327943583},{"rank":148,"player_name":"AtlasThirteen","rank_name":"Grandmaster 3","score":4554,"matches":70,"player_id":2011654320},{"rank":149,"player_name":"Chainsawpirate","rank_name":"Grandmaster 3","score":4554,"matches":163,"player_id":798162349},{"rank":150,"player_name":"Robin_KTAP","rank_name":"Grandmaster 3","score":4553,"matches":93,"player_id":1996677760},{"rank":151,"player_name":"Aresx61","rank_name":"Grandmaster 3","score":4549,"matches":161,"player_id":1100394959},{"rank":152,"player_name":"Tuviee","rank_name":"Grandmaster 3","score":4548,"matches":126,"player_id":976340605},{"rank":153,"player_name":"A-tech","rank_name":"Grandmaster 3","score":4546,"matches":53,"player_id":941850294},{"rank":154,"player_name":"div1s1on","rank_name":"Grandmaster 3","score":4545,"matches":95,"player_id":715330646},{"rank":155,"player_name":"SheikDaddy","rank_name":"Grandmaster 3","score":4544,"matches":115,"player_id":629153120},{"rank":156,"player_name":"Jonaphx","rank_name":"Grandmaster 3","score":4544,"matches":59,"player_id":472737741},{"rank":157,"player_name":"dxvey","rank_name":"Grandmaster 3","score":4543,"matches":119,"player_id":2046629552},{"rank":158,"player_name":"TTV_SHALALAKA","rank_name":"Grandmaster 3","score":4543,"matches":95,"player_id":1680902126},{"rank":159,"player_name":"bossin2005","rank_name":"Grandmaster 3","score":4542,"matches":58,"player_id":215689550},{"rank":160,"player_name":"tridvajedan","rank_name":"Grandmaster 3","score":4541,"matches":69,"player_id":1562056177},{"rank":161,"player_name":"Kelminator","rank_name":"Grandmaster 3","score":4537,"matches":53,"player_id":702595529},{"rank":162,"player_name":"ADIVENGER","rank_name":"Grandmaster 3","score":4535,"matches":89,"player_id":129762554},{"rank":163,"player_name":"DevvoSMASH","rank_name":"Grandmaster 3","score":4535,"matches":59,"player_id":459132361},{"rank":164,"player_name":"13commits53","rank_name":"Grandmaster 3","score":4534,"matches":109,"player_id":1528428949},{"rank":165,"player_name":"IAmTheLich","rank_name":"Grandmaster 3","score":4533,"matches":102,"player_id":1776150764},{"rank":166,"player_name":"Baby Tate","rank_name":"Grandmaster 3","score":4531,"matches":107,"player_id":444748652},{"rank":167,"player_name":"Reciting","rank_name":"Grandmaster 3","score":4529,"matches":63,"player_id":1142320730},{"rank":168,"player_name":"CuteToeLicker","rank_name":"Grandmaster 3","score":4529,"matches":60,"player_id":1762366852},{"rank":169,"player_name":"BEASTAAA","rank_name":"Grandmaster 3","score":4528,"matches":86,"player_id":1447183538},{"rank":170,"player_name":"OnePieceLoki","rank_name":"Grandmaster 3","score":4528,"matches":52,"player_id":1536295386},{"rank":171,"player_name":"Griffith 52","rank_name":"Grandmaster 3","score":4528,"matches":63,"player_id":964229540},{"rank":172,"player_name":"Skeever","rank_name":"Grandmaster 3","score":4527,"matches":57,"player_id":70277333},{"rank":173,"player_name":"cashmoney-","rank_name":"Grandmaster 3","score":4526,"matches":130,"player_id":1518684761},{"rank":174,"player_name":"Elsoushi","rank_name":"Grandmaster 3","score":4524,"matches":137,"player_id":961273525},{"rank":175,"player_name":"FrizzleDrizzle","rank_name":"Grandmaster 3","score":4524,"matches":95,"player_id":1501301548},{"rank":176,"player_name":"TAX-EVADER-MAN","rank_name":"Grandmaster 3","score":4524,"matches":115,"player_id":719382379},{"rank":177,"player_name":"-Niru","rank_name":"Grandmaster 3","score":4522,"matches":56,"player_id":1777701771},{"rank":178,"player_name":"Escape Fr0m OW","rank_name":"Grandmaster 3","score":4519,"matches":52,"player_id":1424069056},{"rank":179,"player_name":"Cyrapite","rank_name":"Grandmaster 3","score":4517,"matches":120,"player_id":197565379},{"rank":180,"player_name":"Jinn_07","rank_name":"Grandmaster 3","score":4517,"matches":122,"player_id":596822720},{"rank":181,"player_name":"monstrixx","rank_name":"Grandmaster 3","score":4517,"matches":81,"player_id":270647088},{"rank":182,"player_name":"Hellzak","rank_name":"Grandmaster 3","score":4516,"matches":59,"player_id":95967380},{"rank":183,"player_name":"Sixxes","rank_name":"Grandmaster 3","score":4516,"matches":53,"player_id":542315470},{"rank":184,"player_name":"spearr","rank_name":"Grandmaster 3","score":4516,"matches":57,"player_id":1458594254},{"rank":185,"player_name":"Lasor Beam","rank_name":"Grandmaster 3","score":4515,"matches":55,"player_id":1966086053},{"rank":186,"player_name":"Captain Banjax","rank_name":"Grandmaster 3","score":4513,"matches":56,"player_id":614304624},{"rank":187,"player_name":"Lagra","rank_name":"Grandmaster 3","score":4513,"matches":78,"player_id":1205175671},{"rank":188,"player_name":"ReZGamehunter","rank_name":"Grandmaster 3","score":4513,"matches":86,"player_id":1475212967},{"rank":189,"player_name":"Brain d3ad","rank_name":"Grandmaster 3","score":4511,"matches":73,"player_id":1787293500},{"rank":190,"player_name":"-PixiePowder-","rank_name":"Grandmaster 3","score":4511,"matches":77,"player_id":1974469127},{"rank":191,"player_name":"Phantom4drone","rank_name":"Grandmaster 3","score":4510,"matches":144,"player_id":1785869201},{"rank":192,"player_name":"44KingKong44","rank_name":"Grandmaster 3","score":4510,"matches":65,"player_id":134805547},{"rank":193,"player_name":"Krivid","rank_name":"Grandmaster 3","score":4509,"matches":70,"player_id":1200200466},{"rank":194,"player_name":"Robsterhui24","rank_name":"Grandmaster 3","score":4509,"matches":55,"player_id":1151029915},{"rank":195,"player_name":"GoodJobBigMan","rank_name":"Grandmaster 3","score":4508,"matches":73,"player_id":191183127},{"rank":196,"player_name":"ChrisGotHeat23","rank_name":"Grandmaster 3","score":4506,"matches":70,"player_id":2117217383},{"rank":197,"player_name":"A2nSensation","rank_name":"Grandmaster 3","score":4505,"matches":208,"player_id":1233155820},{"rank":198,"player_name":"Trickyo","rank_name":"Grandmaster 3","score":4505,"matches":116,"player_id":1691050547},{"rank":199,"player_name":"MrLngtip","rank_name":"Grandmaster 3","score":4504,"matches":227,"player_id":305102323},{"rank":200,"player_name":"Marinette","rank_name":"Grandmaster 3","score":4504,"matches":56,"player_id":1744007276},{"rank":201,"player_name":"ConscriptSpidr","rank_name":"Grandmaster 3","score":4503,"matches":61,"player_id":423923127},{"rank":202,"player_name":"Cabal","rank_name":"Grandmaster 3","score":4502,"matches":62,"player_id":143823389},{"rank":203,"player_name":"Maityz","rank_name":"Grandmaster 3","score":4501,"matches":58,"player_id":846783142},{"rank":204,"player_name":"The Pixel","rank_name":"Grandmaster 3","score":4501,"matches":220,"player_id":587724333},{"rank":205,"player_name":"tmdeej","rank_name":"Grandmaster 3","score":4500,"matches":86,"player_id":1228816456},{"rank":206,"player_name":"listlesszk","rank_name":"Grandmaster 3","score":4500,"matches":90,"player_id":1110244192},{"rank":207,"player_name":"SPEEDBREAKER_","rank_name":"Grandmaster 3","score":4497,"matches":113,"player_id":648620444},{"rank":208,"player_name":"Caldur's Gate","rank_name":"Grandmaster 3","score":4495,"matches":57,"player_id":1048021395},{"rank":209,"player_name":"破虚妄","rank_name":"Grandmaster 3","score":4494,"matches":51,"player_id":675533121},{"rank":210,"player_name":"Lokzmir","rank_name":"Grandmaster 3","score":4493,"matches":67,"player_id":1113771182},{"rank":211,"player_name":"MasnoGrom","rank_name":"Diamond 1","score":4493,"matches":53,"player_id":10588162},{"rank":212,"player_name":"eren-jodd","rank_name":"Grandmaster 3","score":4492,"matches":93,"player_id":12225902},{"rank":213,"player_name":"erxc319","rank_name":"Grandmaster 3","score":4491,"matches":76,"player_id":511260028},{"rank":214,"player_name":"Hnto","rank_name":"Grandmaster 3","score":4489,"matches":56,"player_id":1826753135},{"rank":215,"player_name":"Stone Nuts","rank_name":"Grandmaster 3","score":4484,"matches":123,"player_id":1846789445},{"rank":216,"player_name":"qyhqnqbi","rank_name":"Grandmaster 3","score":4483,"matches":104,"player_id":552224654},{"rank":217,"player_name":"NXCloudyTwitch","rank_name":"Grandmaster 3","score":4482,"matches":189,"player_id":1033079638},{"rank":218,"player_name":"HastarYoutube","rank_name":"Diamond 1","score":4481,"matches":90,"player_id":1581311662},{"rank":219,"player_name":"SpecialXBeam","rank_name":"Grandmaster 3","score":4481,"matches":61,"player_id":1936181872},{"rank":220,"player_name":"FlaggerM","rank_name":"Grandmaster 3","score":4481,"matches":146,"player_id":1215443965},{"rank":221,"player_name":"ABiscool","rank_name":"Diamond 1","score":4481,"matches":106,"player_id":211568238},{"rank":222,"player_name":"MoveMyCar","rank_name":"Diamond 1","score":4478,"matches":72,"player_id":847196577},{"rank":223,"player_name":"Zennification-","rank_name":"Diamond 1","score":4478,"matches":53,"player_id":1987881000},{"rank":224,"player_name":"ChiefShields","rank_name":"Grandmaster 3","score":4476,"matches":74,"player_id":1881117873},{"rank":225,"player_name":"Nikitoske","rank_name":"Diamond 1","score":4476,"matches":61,"player_id":1509487212},{"rank":226,"player_name":"Afflixn","rank_name":"Diamond 1","score":4475,"matches":91,"player_id":307902457},{"rank":227,"player_name":"yuishii","rank_name":"Grandmaster 3","score":4473,"matches":81,"player_id":1221957457},{"rank":228,"player_name":"ApnaBazaar","rank_name":"Diamond 1","score":4472,"matches":87,"player_id":1380645025},{"rank":229,"player_name":"rooseve1t","rank_name":"Diamond 1","score":4471,"matches":93,"player_id":319137114},{"rank":230,"player_name":"The Wheezer","rank_name":"Grandmaster 3","score":4470,"matches":115,"player_id":616817643},{"rank":231,"player_name":"Jaaxfulᵗᵗᵛ","rank_name":"Grandmaster 3","score":4470,"matches":88,"player_id":253532506},{"rank":232,"player_name":"GorillaManee","rank_name":"Grandmaster 3","score":4470,"matches":79,"player_id":1116103712},{"rank":233,"player_name":"gh0st","rank_name":"Diamond 1","score":4469,"matches":89,"player_id":1894001606},{"rank":234,"player_name":"Teegco","rank_name":"Diamond 1","score":4467,"matches":67,"player_id":143361070},{"rank":235,"player_name":"TTV_DDog","rank_name":"Diamond 1","score":4467,"matches":297,"player_id":1803754327},{"rank":236,"player_name":"minniio","rank_name":"Diamond 1","score":4467,"matches":85,"player_id":77413019},{"rank":237,"player_name":"arty._","rank_name":"Diamond 1","score":4465,"matches":71,"player_id":216213334},{"rank":238,"player_name":"Styx6363","rank_name":"Diamond 1","score":4465,"matches":52,"player_id":1317796303},{"rank":239,"player_name":"Reespo","rank_name":"Diamond 1","score":4460,"matches":54,"player_id":1441967602},{"rank":240,"player_name":"cocadust","rank_name":"Diamond 1","score":4457,"matches":189,"player_id":1726171444},{"rank":241,"player_name":"Shinytrousers","rank_name":"Diamond 1","score":4457,"matches":64,"player_id":1296298280},{"rank":242,"player_name":"neighborpls","rank_name":"Diamond 1","score":4454,"matches":71,"player_id":173924471},{"rank":243,"player_name":"BaarMoedrVoedr","rank_name":"Diamond 1","score":4454,"matches":133,"player_id":2107922602},{"rank":244,"player_name":"YBx3","rank_name":"Diamond 1","score":4454,"matches":123,"player_id":726312647},{"rank":245,"player_name":"Temptalking","rank_name":"Diamond 1","score":4451,"matches":87,"player_id":1413844225},{"rank":246,"player_name":"N A N I","rank_name":"Diamond 1","score":4450,"matches":60,"player_id":468646334},{"rank":247,"player_name":"MrWestTTV","rank_name":"Diamond 1","score":4450,"matches":207,"player_id":1185739632},{"rank":248,"player_name":"Katon Endan","rank_name":"Diamond 1","score":4448,"matches":95,"player_id":1835988490},{"rank":249,"player_name":"kasperNova","rank_name":"Diamond 1","score":4448,"matches":56,"player_id":1561969069},{"rank":250,"player_name":"SkillmaticK","rank_name":"Diamond 1","score":4447,"matches":115,"player_id":305623930},{"rank":251,"player_name":"UnSpotted","rank_name":"Diamond 1","score":4442,"matches":63,"player_id":1065234337},{"rank":252,"player_name":"PooPooheadLIVE","rank_name":"Diamond 1","score":4442,"matches":61,"player_id":1765489647},{"rank":253,"player_name":"JebisBread","rank_name":"Diamond 1","score":4441,"matches":56,"player_id":707555898},{"rank":254,"player_name":"VolticPhantom","rank_name":"Diamond 1","score":4439,"matches":69,"player_id":766355548},{"rank":255,"player_name":"GalosDJ","rank_name":"Diamond 1","score":4437,"matches":113,"player_id":1650586874},{"rank":256,"player_name":"roos235","rank_name":"Diamond 1","score":4436,"matches":113,"player_id":2009301971},{"rank":257,"player_name":"Persias","rank_name":"Diamond 1","score":4435,"matches":88,"player_id":1401238777},{"rank":258,"player_name":"Ozrukar","rank_name":"Diamond 1","score":4435,"matches":101,"player_id":2017180387},{"rank":259,"player_name":"Xendol","rank_name":"Diamond 1","score":4435,"matches":89,"player_id":483256649},{"rank":260,"player_name":"DEI-hire","rank_name":"Diamond 1","score":4435,"matches":62,"player_id":549575657},{"rank":261,"player_name":"small_shard","rank_name":"Diamond 1","score":4433,"matches":122,"player_id":32548524},{"rank":262,"player_name":"lowdiddler","rank_name":"Diamond 1","score":4433,"matches":69,"player_id":222502459},{"rank":263,"player_name":"PullUpShootin","rank_name":"Diamond 1","score":4432,"matches":68,"player_id":720978224},{"rank":264,"player_name":"Se3fy","rank_name":"Diamond 1","score":4431,"matches":61,"player_id":830834117},{"rank":265,"player_name":"Jaydog108","rank_name":"Diamond 1","score":4428,"matches":63,"player_id":1686222225},{"rank":266,"player_name":"spirit'","rank_name":"Diamond 1","score":4427,"matches":78,"player_id":964174157},{"rank":267,"player_name":"TheGrid1006","rank_name":"Diamond 1","score":4427,"matches":58,"player_id":521838413},{"rank":268,"player_name":"icy_bo","rank_name":"Diamond 1","score":4426,"matches":157,"player_id":1803022749},{"rank":269,"player_name":"UltraX_2003","rank_name":"Diamond 1","score":4425,"matches":215,"player_id":351399888},{"rank":270,"player_name":"Descö","rank_name":"Diamond 1","score":4425,"matches":99,"player_id":1312610329},{"rank":271,"player_name":"Tatie-Huguette","rank_name":"Diamond 1","score":4425,"matches":97,"player_id":929974272},{"rank":272,"player_name":"Wikie","rank_name":"Diamond 1","score":4424,"matches":92,"player_id":1826438116},{"rank":273,"player_name":"Tyn x","rank_name":"Diamond 1","score":4423,"matches":106,"player_id":540135732},{"rank":274,"player_name":"Jdarock12","rank_name":"Diamond 1","score":4423,"matches":64,"player_id":580046548},{"rank":275,"player_name":"Kwlashots","rank_name":"Diamond 1","score":4422,"matches":102,"player_id":940577896},{"rank":276,"player_name":"NesnahOG","rank_name":"Diamond 1","score":4422,"matches":63,"player_id":296015640},{"rank":277,"player_name":"H2NT3R9","rank_name":"Diamond 1","score":4422,"matches":216,"player_id":774259272},{"rank":278,"player_name":"yvr-z","rank_name":"Diamond 1","score":4420,"matches":99,"player_id":1895191751},{"rank":279,"player_name":"wetchief","rank_name":"Diamond 1","score":4419,"matches":77,"player_id":719661149},{"rank":280,"player_name":"MelloL","rank_name":"Diamond 1","score":4419,"matches":58,"player_id":2000562644},{"rank":281,"player_name":"QUΙNN","rank_name":"Diamond 1","score":4417,"matches":253,"player_id":445485374},{"rank":282,"player_name":"MageFounderTTV","rank_name":"Diamond 1","score":4417,"matches":194,"player_id":1774764265},{"rank":283,"player_name":"hamsters","rank_name":"Diamond 1","score":4416,"matches":70,"player_id":2031906283},{"rank":284,"player_name":"EngulfingSlime","rank_name":"Diamond 1","score":4414,"matches":55,"player_id":1185983710},{"rank":285,"player_name":".N.","rank_name":"Diamond 1","score":4413,"matches":86,"player_id":2015766332},{"rank":286,"player_name":"_Dane_","rank_name":"Diamond 1","score":4411,"matches":56,"player_id":1291142646},{"rank":287,"player_name":"HowDoIPlayLeft","rank_name":"Diamond 1","score":4409,"matches":112,"player_id":561764123},{"rank":288,"player_name":"Freshwaterツ","rank_name":"Diamond 1","score":4409,"matches":180,"player_id":1773747028},{"rank":289,"player_name":"bobyblanquita","rank_name":"Diamond 1","score":4408,"matches":69,"player_id":1251621685},{"rank":290,"player_name":"Sigma_Gaming52","rank_name":"Diamond 1","score":4408,"matches":260,"player_id":1809641562},{"rank":291,"player_name":"jayls8","rank_name":"Diamond 1","score":4407,"matches":70,"player_id":1138571871},{"rank":292,"player_name":"Dontbanme","rank_name":"Diamond 1","score":4407,"matches":101,"player_id":1735049331},{"rank":293,"player_name":"Ponnop","rank_name":"Diamond 1","score":4406,"matches":57,"player_id":1138753789},{"rank":294,"player_name":"Scribblerz","rank_name":"Diamond 1","score":4405,"matches":67,"player_id":616295290},{"rank":295,"player_name":"iykZANGETSU","rank_name":"Diamond 1","score":4405,"matches":82,"player_id":1248710168},{"rank":296,"player_name":"Aurorioum","rank_name":"Diamond 1","score":4405,"matches":83,"player_id":325450895},{"rank":297,"player_name":"StepOnMePsy","rank_name":"Diamond 1","score":4399,"matches":83,"player_id":914899177},{"rank":298,"player_name":"SkinnyDinky","rank_name":"Diamond 1","score":4399,"matches":62,"player_id":1783136856},{"rank":299,"player_name":"notstealth_","rank_name":"Diamond 1","score":4398,"matches":157,"player_id":587984890},{"rank":300,"player_name":"TTVdriftr_g3","rank_name":"Diamond 2","score":4398,"matches":244,"player_id":288396614},{"rank":301,"player_name":"orvini_10","rank_name":"Diamond 2","score":4397,"matches":219,"player_id":72104141},{"rank":302,"player_name":"daddypepa","rank_name":"Diamond 1","score":4397,"matches":163,"player_id":1284011607},{"rank":303,"player_name":"Razzebuseman","rank_name":"Diamond 1","score":4395,"matches":207,"player_id":1067092597},{"rank":304,"player_name":"bluiemoon","rank_name":"Diamond 1","score":4394,"matches":95,"player_id":60360964},{"rank":305,"player_name":"Golemed","rank_name":"Diamond 1","score":4394,"matches":59,"player_id":1284173217},{"rank":306,"player_name":"ckod","rank_name":"Diamond 2","score":4391,"matches":72,"player_id":858217752},{"rank":307,"player_name":"Shostakova","rank_name":"Diamond 1","score":4390,"matches":103,"player_id":460891556},{"rank":308,"player_name":"Lanzette","rank_name":"Diamond 1","score":4389,"matches":51,"player_id":844971086},{"rank":309,"player_name":"xicoesperto","rank_name":"Diamond 1","score":4388,"matches":91,"player_id":2065917706},{"rank":310,"player_name":"ESQ7Zbj","rank_name":"Diamond 1","score":4387,"matches":68,"player_id":1183415439},{"rank":311,"player_name":"A1ML0CK","rank_name":"Diamond 1","score":4386,"matches":299,"player_id":2006777830},{"rank":312,"player_name":"We3no","rank_name":"Diamond 2","score":4386,"matches":65,"player_id":1659286556},{"rank":313,"player_name":"Nde","rank_name":"Diamond 1","score":4385,"matches":99,"player_id":1490593381},{"rank":314,"player_name":"allrange","rank_name":"Diamond 1","score":4381,"matches":60,"player_id":341990618},{"rank":315,"player_name":"P1V1mRT1","rank_name":"Diamond 1","score":4380,"matches":62,"player_id":1145163410},{"rank":316,"player_name":"SirMrDrGod","rank_name":"Diamond 1","score":4379,"matches":302,"player_id":395644640},{"rank":317,"player_name":"Zork-kw","rank_name":"Diamond 2","score":4373,"matches":57,"player_id":2025041274},{"rank":318,"player_name":".IAmTheMilkMan","rank_name":"Diamond 2","score":4373,"matches":196,"player_id":1747078467},{"rank":319,"player_name":"pkmelee","rank_name":"Diamond 2","score":4372,"matches":56,"player_id":829902530},{"rank":320,"player_name":"Smashin","rank_name":"Diamond 2","score":4372,"matches":55,"player_id":83290818},{"rank":321,"player_name":"zoinkai","rank_name":"Diamond 2","score":4371,"matches":92,"player_id":974245134},{"rank":322,"player_name":"Dinglebob195","rank_name":"Diamond 2","score":4369,"matches":83,"player_id":559271614},{"rank":323,"player_name":"SunCorcoran","rank_name":"Diamond 2","score":4367,"matches":123,"player_id":1289390058},{"rank":324,"player_name":"Ax24","rank_name":"Diamond 2","score":4366,"matches":77,"player_id":2079010748},{"rank":325,"player_name":"Dility","rank_name":"Diamond 2","score":4365,"matches":53,"player_id":1711103126},{"rank":326,"player_name":"J.A.R.V.I.Sr34","rank_name":"Diamond 2","score":4365,"matches":86,"player_id":865069763},{"rank":327,"player_name":"Siteev","rank_name":"Diamond 2","score":4365,"matches":160,"player_id":50577696},{"rank":328,"player_name":"Doom_hunter","rank_name":"Diamond 2","score":4364,"matches":104,"player_id":1140568996},{"rank":329,"player_name":"SquirmLikeWorm","rank_name":"Diamond 2","score":4363,"matches":51,"player_id":1431736385},{"rank":330,"player_name":"IP_Shin","rank_name":"Diamond 2","score":4363,"matches":83,"player_id":473231467},{"rank":331,"player_name":"ZeroNull5","rank_name":"Diamond 2","score":4363,"matches":121,"player_id":632380536},{"rank":332,"player_name":"CTP4X4-HET","rank_name":"Diamond 2","score":4363,"matches":53,"player_id":1550792132},{"rank":333,"player_name":"Yajuuj","rank_name":"Diamond 2","score":4362,"matches":95,"player_id":81503992},{"rank":334,"player_name":"Stepback J","rank_name":"Diamond 2","score":4360,"matches":89,"player_id":284086899},{"rank":335,"player_name":"Megapkmn77","rank_name":"Diamond 2","score":4355,"matches":73,"player_id":326530293},{"rank":336,"player_name":"Geckster","rank_name":"Diamond 2","score":4352,"matches":240,"player_id":845478706},{"rank":337,"player_name":"Napkino","rank_name":"Diamond 2","score":4351,"matches":81,"player_id":283401110},{"rank":338,"player_name":"<RileyCantReid","rank_name":"Diamond 2","score":4349,"matches":61,"player_id":1395872867},{"rank":339,"player_name":"lockdowncrown","rank_name":"Diamond 2","score":4349,"matches":91,"player_id":1315225250},{"rank":340,"player_name":"TGamerPT","rank_name":"Diamond 2","score":4349,"matches":64,"player_id":851782185},{"rank":341,"player_name":"HenryIsBack","rank_name":"Diamond 2","score":4349,"matches":52,"player_id":654622797},{"rank":342,"player_name":"Influancia","rank_name":"Diamond 2","score":4346,"matches":88,"player_id":2067356570},{"rank":343,"player_name":"Merlin5488","rank_name":"Diamond 2","score":4345,"matches":72,"player_id":1513513687},{"rank":344,"player_name":"Sterson","rank_name":"Diamond 2","score":4343,"matches":151,"player_id":1023764894},{"rank":345,"player_name":"ChampionGGs","rank_name":"Diamond 2","score":4341,"matches":95,"player_id":1111805462},{"rank":346,"player_name":"Shaduk","rank_name":"Diamond 2","score":4339,"matches":124,"player_id":1644753407},{"rank":347,"player_name":"reptiIe.","rank_name":"Diamond 2","score":4338,"matches":90,"player_id":1032259825},{"rank":348,"player_name":"Fudge73","rank_name":"Diamond 2","score":4335,"matches":58,"player_id":159224075},{"rank":349,"player_name":"Asznee","rank_name":"Diamond 2","score":4334,"matches":101,"player_id":1784094309},{"rank":350,"player_name":"JohnYipeeKiYay","rank_name":"Diamond 2","score":4332,"matches":58,"player_id":1206370684},{"rank":351,"player_name":"Cripjaw","rank_name":"Diamond 2","score":4331,"matches":153,"player_id":1303678972},{"rank":352,"player_name":"ForgedLives","rank_name":"Diamond 2","score":4331,"matches":120,"player_id":1869447148},{"rank":353,"player_name":"wavecxz228","rank_name":"Diamond 2","score":4331,"matches":75,"player_id":751197550},{"rank":354,"player_name":"twinwastaken","rank_name":"Diamond 2","score":4329,"matches":80,"player_id":619165644},{"rank":355,"player_name":"ipinkies","rank_name":"Diamond 2","score":4328,"matches":74,"player_id":799542696},{"rank":356,"player_name":"KCGuna","rank_name":"Diamond 2","score":4328,"matches":67,"player_id":1913809908},{"rank":357,"player_name":"FlamingTiger31","rank_name":"Diamond 2","score":4324,"matches":81,"player_id":945876033},{"rank":358,"player_name":"Firexf3","rank_name":"Diamond 2","score":4324,"matches":142,"player_id":1698814105},{"rank":359,"player_name":"ChoogaBooga","rank_name":"Diamond 2","score":4323,"matches":62,"player_id":1298167455},{"rank":360,"player_name":"Brandingdong","rank_name":"Diamond 2","score":4322,"matches":374,"player_id":2006653768},{"rank":361,"player_name":"Zecret4k","rank_name":"Diamond 2","score":4321,"matches":70,"player_id":423218765},{"rank":362,"player_name":"HuIkbuster","rank_name":"Diamond 2","score":4318,"matches":187,"player_id":2047494759},{"rank":363,"player_name":"Carthaginian33","rank_name":"Diamond 2","score":4318,"matches":68,"player_id":542116700},{"rank":364,"player_name":"Hildacım","rank_name":"Diamond 2","score":4317,"matches":144,"player_id":1155260977},{"rank":365,"player_name":"MinimumPulsee","rank_name":"Diamond 2","score":4316,"matches":104,"player_id":1986861832},{"rank":366,"player_name":"Barry_","rank_name":"Diamond 2","score":4316,"matches":61,"player_id":856679818},{"rank":367,"player_name":"blueimoon","rank_name":"Diamond 2","score":4316,"matches":112,"player_id":2115729519},{"rank":368,"player_name":"stelioslim","rank_name":"Diamond 2","score":4315,"matches":57,"player_id":1239293481},{"rank":369,"player_name":"Vronathan","rank_name":"Diamond 2","score":4314,"matches":73,"player_id":2129946590},{"rank":370,"player_name":"Yersei","rank_name":"Diamond 2","score":4312,"matches":154,"player_id":423817814},{"rank":371,"player_name":"Gumoo","rank_name":"Diamond 2","score":4312,"matches":68,"player_id":1236678626},{"rank":372,"player_name":"ANXX","rank_name":"Diamond 2","score":4310,"matches":113,"player_id":743487358},{"rank":373,"player_name":"Jarvis Simp","rank_name":"Diamond 2","score":4310,"matches":89,"player_id":2091369008},{"rank":374,"player_name":"Anthonyontv","rank_name":"Diamond 2","score":4309,"matches":106,"player_id":1876873582},{"rank":375,"player_name":"HAHAUMADZ","rank_name":"Diamond 2","score":4309,"matches":71,"player_id":556651813},{"rank":376,"player_name":"Thepixsans","rank_name":"Diamond 2","score":4308,"matches":94,"player_id":735916321},{"rank":377,"player_name":"BlueAdam03","rank_name":"Diamond 2","score":4307,"matches":62,"player_id":2088813575},{"rank":378,"player_name":"Banane44","rank_name":"Diamond 2","score":4305,"matches":78,"player_id":702809048},{"rank":379,"player_name":"Terabium","rank_name":"Diamond 2","score":4305,"matches":135,"player_id":1254829095},{"rank":380,"player_name":"dxubtful","rank_name":"Diamond 2","score":4304,"matches":51,"player_id":876039028},{"rank":381,"player_name":"MilkMeSlow","rank_name":"Diamond 2","score":4304,"matches":57,"player_id":2022393766},{"rank":382,"player_name":"__fear__","rank_name":"Diamond 2","score":4304,"matches":102,"player_id":2027973006},{"rank":383,"player_name":"BienNalgon","rank_name":"Diamond 2","score":4303,"matches":57,"player_id":2040639954},{"rank":384,"player_name":"Voli_VEVO","rank_name":"Diamond 2","score":4302,"matches":141,"player_id":1936121389},{"rank":385,"player_name":"fakehuntorious","rank_name":"Diamond 2","score":4302,"matches":211,"player_id":1454205037},{"rank":386,"player_name":"AoeSega","rank_name":"Diamond 3","score":4299,"matches":73,"player_id":285056649},{"rank":387,"player_name":"KingJulianDC","rank_name":"Diamond 2","score":4299,"matches":72,"player_id":762327396},{"rank":388,"player_name":"khldy","rank_name":"Diamond 2","score":4297,"matches":141,"player_id":316713787},{"rank":389,"player_name":"zhinoe","rank_name":"Diamond 2","score":4296,"matches":62,"player_id":770402640},{"rank":390,"player_name":"dont4botpls","rank_name":"Diamond 2","score":4295,"matches":134,"player_id":1467637919},{"rank":391,"player_name":"Backspace098","rank_name":"Diamond 2","score":4295,"matches":90,"player_id":1122290089},{"rank":392,"player_name":"Peponcio69","rank_name":"Diamond 2","score":4295,"matches":87,"player_id":1486766226},{"rank":393,"player_name":"T1 Wolf","rank_name":"Diamond 3","score":4294,"matches":132,"player_id":476703636},{"rank":394,"player_name":"coooldude713","rank_name":"Diamond 2","score":4293,"matches":159,"player_id":1061008527},{"rank":395,"player_name":"SageKid","rank_name":"Diamond 3","score":4291,"matches":69,"player_id":455908397},{"rank":396,"player_name":"ItsHiroh","rank_name":"Diamond 2","score":4290,"matches":71,"player_id":1372953575},{"rank":397,"player_name":"Jeff DPS Shark","rank_name":"Diamond 3","score":4290,"matches":74,"player_id":1080455259},{"rank":398,"player_name":"ClipThatShiet","rank_name":"Diamond 2","score":4287,"matches":51,"player_id":1749477820},{"rank":399,"player_name":"Hermes_Hyd","rank_name":"Diamond 2","score":4287,"matches":71,"player_id":301022857},{"rank":400,"player_name":"froguakecros","rank_name":"Diamond 3","score":4286,"matches":57,"player_id":1007077080},{"rank":401,"player_name":"CMOON27","rank_name":"Diamond 3","score":4286,"matches":101,"player_id":2115325961},{"rank":402,"player_name":"The_Bus","rank_name":"Diamond 2","score":4285,"matches":53,"player_id":253658035},{"rank":403,"player_name":"o0fis","rank_name":"Diamond 3","score":4284,"matches":246,"player_id":363738940},{"rank":404,"player_name":"Noonki","rank_name":"Diamond 2","score":4284,"matches":69,"player_id":82274269},{"rank":405,"player_name":"ZOL7_","rank_name":"Diamond 2","score":4284,"matches":71,"player_id":1915360523},{"rank":406,"player_name":"Womec","rank_name":"Diamond 3","score":4284,"matches":55,"player_id":870575396},{"rank":407,"player_name":"FieryCasey","rank_name":"Diamond 3","score":4281,"matches":61,"player_id":2012161781},{"rank":408,"player_name":"JEclipze","rank_name":"Diamond 3","score":4280,"matches":53,"player_id":1790994627},{"rank":409,"player_name":"ViSiOnzz808","rank_name":"Diamond 3","score":4279,"matches":61,"player_id":1741859043},{"rank":410,"player_name":"Bronx-a2k","rank_name":"Diamond 3","score":4278,"matches":74,"player_id":485564},{"rank":411,"player_name":"Woof__","rank_name":"Diamond 3","score":4277,"matches":66,"player_id":1979570400},{"rank":412,"player_name":"LightzYT","rank_name":"Diamond 3","score":4277,"matches":56,"player_id":678275609},{"rank":413,"player_name":"DiddyMau","rank_name":"Diamond 2","score":4277,"matches":89,"player_id":15259431},{"rank":414,"player_name":"butttz","rank_name":"Diamond 3","score":4276,"matches":61,"player_id":516933195},{"rank":415,"player_name":"dizel913","rank_name":"Diamond 3","score":4275,"matches":91,"player_id":1874672066},{"rank":416,"player_name":"BiggumsThicums","rank_name":"Diamond 3","score":4274,"matches":79,"player_id":1059308465},{"rank":417,"player_name":"ThexBest1","rank_name":"Diamond 2","score":4273,"matches":155,"player_id":1461270583},{"rank":418,"player_name":"EAtashi","rank_name":"Diamond 3","score":4273,"matches":52,"player_id":442787851},{"rank":419,"player_name":"MadFShadows","rank_name":"Diamond 3","score":4271,"matches":96,"player_id":107011637},{"rank":420,"player_name":"Adauchi","rank_name":"Diamond 3","score":4269,"matches":127,"player_id":1547246687},{"rank":421,"player_name":"Irоn Mаn","rank_name":"Diamond 3","score":4269,"matches":156,"player_id":1243585476},{"rank":422,"player_name":"ORIYAIN","rank_name":"Diamond 3","score":4269,"matches":52,"player_id":665587959},{"rank":423,"player_name":"RenegadeSlayer","rank_name":"Diamond 3","score":4268,"matches":147,"player_id":58985049},{"rank":424,"player_name":"Whyamisobaddog","rank_name":"Diamond 3","score":4268,"matches":92,"player_id":1557563453},{"rank":425,"player_name":"SweetCainMusic","rank_name":"Diamond 3","score":4267,"matches":71,"player_id":1228610899},{"rank":426,"player_name":"Sharizard","rank_name":"Diamond 3","score":4267,"matches":120,"player_id":94392499},{"rank":427,"player_name":"LakshayGOD","rank_name":"Diamond 3","score":4266,"matches":82,"player_id":742923391},{"rank":428,"player_name":"Jaco1022","rank_name":"Diamond 3","score":4266,"matches":71,"player_id":177569590},{"rank":429,"player_name":"NineTaleddog","rank_name":"Diamond 3","score":4265,"matches":113,"player_id":1192196859},{"rank":430,"player_name":"Lynnn-","rank_name":"Diamond 3","score":4265,"matches":76,"player_id":245552185},{"rank":431,"player_name":"i106","rank_name":"Diamond 3","score":4264,"matches":73,"player_id":1954028970},{"rank":432,"player_name":"Lassiie","rank_name":"Diamond 3","score":4264,"matches":70,"player_id":671073576},{"rank":433,"player_name":"LimpBizkt","rank_name":"Diamond 3","score":4262,"matches":60,"player_id":1762388429},{"rank":434,"player_name":"Alaric61288","rank_name":"Diamond 3","score":4261,"matches":280,"player_id":145434816},{"rank":435,"player_name":"Dream Lord","rank_name":"Diamond 3","score":4261,"matches":104,"player_id":358227656},{"rank":436,"player_name":"turkzim","rank_name":"Diamond 3","score":4259,"matches":57,"player_id":1392372723},{"rank":437,"player_name":"Kiiro2jz","rank_name":"Diamond 3","score":4258,"matches":54,"player_id":246926480},{"rank":438,"player_name":"PhazeisWashed","rank_name":"Diamond 3","score":4257,"matches":128,"player_id":594529785},{"rank":439,"player_name":"-Niru-","rank_name":"Diamond 3","score":4256,"matches":53,"player_id":2020516680},{"rank":440,"player_name":"nettspendchina","rank_name":"Diamond 3","score":4256,"matches":57,"player_id":154937542},{"rank":441,"player_name":"huntiris","rank_name":"Diamond 3","score":4255,"matches":164,"player_id":1662647296},{"rank":442,"player_name":"TONKA TRUNK","rank_name":"Diamond 3","score":4254,"matches":58,"player_id":1694256418},{"rank":443,"player_name":"crazyboie778","rank_name":"Diamond 3","score":4254,"matches":72,"player_id":146292677},{"rank":444,"player_name":"Ichessepopel","rank_name":"Diamond 3","score":4251,"matches":73,"player_id":437618778},{"rank":445,"player_name":"Itzboom__","rank_name":"Diamond 3","score":4249,"matches":97,"player_id":1823766209},{"rank":446,"player_name":"BAananaBeater","rank_name":"Diamond 3","score":4248,"matches":52,"player_id":1757283322},{"rank":447,"player_name":"kamiofthewest","rank_name":"Diamond 3","score":4247,"matches":66,"player_id":1630672422},{"rank":448,"player_name":"yordleweed","rank_name":"Diamond 3","score":4243,"matches":196,"player_id":920086622},{"rank":449,"player_name":"SignalSiege","rank_name":"Diamond 3","score":4240,"matches":65,"player_id":566950012},{"rank":450,"player_name":"Splashh","rank_name":"Diamond 3","score":4240,"matches":54,"player_id":1669905321},{"rank":451,"player_name":"Smalzor","rank_name":"Diamond 3","score":4240,"matches":62,"player_id":1806008302},{"rank":452,"player_name":"Fekah69","rank_name":"Diamond 3","score":4239,"matches":161,"player_id":937488507},{"rank":453,"player_name":"AntLikesPc","rank_name":"Diamond 3","score":4239,"matches":171,"player_id":470440008},{"rank":454,"player_name":"dazombeslayer","rank_name":"Diamond 3","score":4239,"matches":94,"player_id":82385994},{"rank":455,"player_name":"QKSP","rank_name":"Diamond 3","score":4239,"matches":179,"player_id":1685054737},{"rank":456,"player_name":"TPumpkin","rank_name":"Diamond 3","score":4239,"matches":191,"player_id":803056142},{"rank":457,"player_name":"heolla","rank_name":"Diamond 3","score":4238,"matches":82,"player_id":1973029591},{"rank":458,"player_name":"RadicalNewt","rank_name":"Diamond 3","score":4236,"matches":52,"player_id":1241060189},{"rank":459,"player_name":"Joltze","rank_name":"Diamond 3","score":4236,"matches":65,"player_id":455732012},{"rank":460,"player_name":"Alphaak","rank_name":"Diamond 3","score":4235,"matches":56,"player_id":2132946852},{"rank":461,"player_name":"Mykll","rank_name":"Diamond 3","score":4233,"matches":117,"player_id":1931853713},{"rank":462,"player_name":"goblinmonkey32","rank_name":"Diamond 3","score":4231,"matches":114,"player_id":1274440185},{"rank":463,"player_name":"Sheeba","rank_name":"Diamond 3","score":4231,"matches":61,"player_id":1635880850},{"rank":464,"player_name":"_p1","rank_name":"Diamond 3","score":4230,"matches":75,"player_id":728897249},{"rank":465,"player_name":"E10Sharp","rank_name":"Diamond 3","score":4228,"matches":61,"player_id":670719986},{"rank":466,"player_name":"Esiban","rank_name":"Diamond 3","score":4228,"matches":57,"player_id":729978182},{"rank":467,"player_name":"Hernekeitto","rank_name":"Diamond 3","score":4227,"matches":182,"player_id":1023255986},{"rank":468,"player_name":"Xlien","rank_name":"Diamond 3","score":4226,"matches":52,"player_id":1467229775},{"rank":469,"player_name":"OmarSMOKE","rank_name":"Diamond 3","score":4225,"matches":78,"player_id":680752214},{"rank":470,"player_name":"GDawg915","rank_name":"Diamond 3","score":4225,"matches":63,"player_id":1642127667},{"rank":471,"player_name":"CreamSlurp","rank_name":"Diamond 3","score":4225,"matches":81,"player_id":144523930},{"rank":472,"player_name":"R3no14","rank_name":"Diamond 3","score":4223,"matches":129,"player_id":1519707683},{"rank":473,"player_name":"blackj3sus1","rank_name":"Diamond 3","score":4223,"matches":62,"player_id":1466793546},{"rank":474,"player_name":"ekqmt","rank_name":"Diamond 3","score":4222,"matches":69,"player_id":1744793313},{"rank":475,"player_name":"WindStyle","rank_name":"Diamond 3","score":4222,"matches":123,"player_id":598096712},{"rank":476,"player_name":"Lookup Krawchh","rank_name":"Diamond 3","score":4221,"matches":56,"player_id":378120706},{"rank":477,"player_name":"Redoxium","rank_name":"Diamond 3","score":4220,"matches":103,"player_id":1613440888},{"rank":478,"player_name":"The_Geneticist","rank_name":"Diamond 3","score":4219,"matches":83,"player_id":1989532580},{"rank":479,"player_name":"FloppaFett33","rank_name":"Diamond 3","score":4218,"matches":62,"player_id":593035462},{"rank":480,"player_name":"BurnVEVO","rank_name":"Diamond 3","score":4217,"matches":158,"player_id":1246107427},{"rank":481,"player_name":"EG_01ST","rank_name":"Diamond 3","score":4217,"matches":78,"player_id":575240884},{"rank":482,"player_name":"777LilTMan","rank_name":"Diamond 3","score":4217,"matches":84,"player_id":1259389297},{"rank":483,"player_name":"pantapidis","rank_name":"Diamond 3","score":4216,"matches":138,"player_id":1281253719},{"rank":484,"player_name":"CaptainTitus69","rank_name":"Diamond 3","score":4216,"matches":167,"player_id":735474533},{"rank":485,"player_name":"ittihad3mk","rank_name":"Diamond 3","score":4216,"matches":102,"player_id":1026129289},{"rank":486,"player_name":"Irоn Мan","rank_name":"Diamond 3","score":4216,"matches":73,"player_id":837899533},{"rank":487,"player_name":"H1Moon","rank_name":"Diamond 3","score":4215,"matches":134,"player_id":1753173488},{"rank":488,"player_name":"I_r_o_n-m_a_n","rank_name":"Diamond 3","score":4215,"matches":56,"player_id":1539863903},{"rank":489,"player_name":"MakeGooder","rank_name":"Diamond 3","score":4215,"matches":51,"player_id":883720908},{"rank":490,"player_name":".Brynden.","rank_name":"Diamond 3","score":4214,"matches":66,"player_id":827687345},{"rank":491,"player_name":"GammaTR","rank_name":"Diamond 3","score":4214,"matches":66,"player_id":823082916},{"rank":492,"player_name":"Sharbert","rank_name":"Diamond 3","score":4214,"matches":712,"player_id":487711789},{"rank":493,"player_name":"ゞSignal","rank_name":"Diamond 3","score":4213,"matches":162,"player_id":1417460398},{"rank":494,"player_name":"EverySecCounts","rank_name":"Diamond 3","score":4211,"matches":111,"player_id":1098602739},{"rank":495,"player_name":"GoonKnight4387","rank_name":"Diamond 3","score":4210,"matches":57,"player_id":1280686613},{"rank":496,"player_name":"- Niru -","rank_name":"Diamond 3","score":4210,"matches":51,"player_id":839097960},{"rank":497,"player_name":"00J2NX00","rank_name":"Diamond 3","score":4209,"matches":94,"player_id":987388430},{"rank":498,"player_name":"Iron Wang","rank_name":"Diamond 3","score":4209,"matches":89,"player_id":1305449424},{"rank":499,"player_name":"Wealthy Cow","rank_name":"Diamond 3","score":4208,"matches":51,"player_id":2068512768},{"rank":500,"player_name":"D_Sin","rank_name":"Diamond 3","score":4208,"matches":76,"player_id":1828307852}]