[{"rank":1,"player_name":"Opact","rank_name":"Celestial 1","score":5090,"matches":54,"player_id":127340649},{"rank":2,"player_name":"JoeeOT","rank_name":"Celestial 1","score":5032,"matches":60,"player_id":1451983189},{"rank":3,"player_name":"FatalFrr","rank_name":"Celestial 1","score":4988,"matches":81,"player_id":1034553050},{"rank":4,"player_name":"NiceSpy","rank_name":"Celestial 1","score":4981,"matches":92,"player_id":630265256},{"rank":5,"player_name":"Kryw","rank_name":"Celestial 2","score":4981,"matches":58,"player_id":799467694},{"rank":6,"player_name":"ronaljajaxd","rank_name":"Celestial 2","score":4954,"matches":265,"player_id":1079052458},{"rank":7,"player_name":"ᵈᵛˡ","rank_name":"Celestial 2","score":4941,"matches":57,"player_id":943871262},{"rank":8,"player_name":"toughertuba617","rank_name":"Celestial 2","score":4941,"matches":67,"player_id":1828500506},{"rank":9,"player_name":"WeAreJay","rank_name":"Celestial 2","score":4929,"matches":143,"player_id":1955483280},{"rank":10,"player_name":"Sacrement","rank_name":"Celestial 2","score":4925,"matches":53,"player_id":1132516621},{"rank":11,"player_name":"huskeh","rank_name":"Celestial 2","score":4913,"matches":55,"player_id":127409006},{"rank":12,"player_name":"brosky.","rank_name":"Celestial 2","score":4911,"matches":56,"player_id":956136197},{"rank":13,"player_name":"LewNotSerious","rank_name":"Celestial 2","score":4890,"matches":148,"player_id":871116073},{"rank":14,"player_name":"lnsomniac","rank_name":"Celestial 2","score":4889,"matches":119,"player_id":152126847},{"rank":15,"player_name":"grgrgr","rank_name":"Celestial 3","score":4875,"matches":126,"player_id":2064681561},{"rank":16,"player_name":"elad_ow","rank_name":"Celestial 3","score":4873,"matches":53,"player_id":225017213},{"rank":17,"player_name":"Angadxo","rank_name":"Celestial 3","score":4861,"matches":78,"player_id":1545202546},{"rank":18,"player_name":"WOW R34LLY K1D","rank_name":"Celestial 3","score":4851,"matches":94,"player_id":282055330},{"rank":19,"player_name":"FarmingSoulz","rank_name":"Celestial 3","score":4845,"matches":129,"player_id":2004919368},{"rank":20,"player_name":"Altair2","rank_name":"Celestial 3","score":4835,"matches":51,"player_id":1361039522},{"rank":21,"player_name":"mrstealurgoats","rank_name":"Celestial 3","score":4827,"matches":94,"player_id":1178550403},{"rank":22,"player_name":"Benjer8","rank_name":"Celestial 3","score":4823,"matches":53,"player_id":934961262},{"rank":23,"player_name":"ChooChooWho","rank_name":"Celestial 3","score":4819,"matches":56,"player_id":1005681285},{"rank":24,"player_name":"Darkin774","rank_name":"Celestial 3","score":4818,"matches":85,"player_id":859099484},{"rank":25,"player_name":"Sirequentin","rank_name":"Celestial 3","score":4815,"matches":51,"player_id":2043724940},{"rank":26,"player_name":"Jurassic1n","rank_name":"Celestial 3","score":4813,"matches":176,"player_id":811336683},{"rank":27,"player_name":"KirikoFeetLovr","rank_name":"Celestial 3","score":4812,"matches":72,"player_id":338463065},{"rank":28,"player_name":"Ariancool","rank_name":"Celestial 3","score":4809,"matches":128,"player_id":337158930},{"rank":29,"player_name":"rnzu","rank_name":"Celestial 3","score":4800,"matches":130,"player_id":1925915241},{"rank":30,"player_name":"Kjimi","rank_name":"Celestial 3","score":4789,"matches":157,"player_id":1095935421},{"rank":31,"player_name":"OmObtekar","rank_name":"Grandmaster 1","score":4788,"matches":213,"player_id":714976131},{"rank":32,"player_name":"SigmaMale","rank_name":"Grandmaster 1","score":4788,"matches":79,"player_id":1691803983},{"rank":33,"player_name":"Heliocrash","rank_name":"Celestial 3","score":4782,"matches":201,"player_id":1040995990},{"rank":34,"player_name":"freeze fv","rank_name":"Celestial 3","score":4781,"matches":116,"player_id":398602598},{"rank":35,"player_name":"Jabagas","rank_name":"Celestial 3","score":4773,"matches":59,"player_id":308295252},{"rank":36,"player_name":"Kabzon","rank_name":"Grandmaster 1","score":4767,"matches":53,"player_id":1882463553},{"rank":37,"player_name":"TriXa_Bly4T","rank_name":"Grandmaster 1","score":4763,"matches":130,"player_id":293688015},{"rank":38,"player_name":"Top2chainz","rank_name":"Grandmaster 1","score":4758,"matches":102,"player_id":253754305},{"rank":39,"player_name":"Tbucs","rank_name":"Grandmaster 1","score":4750,"matches":57,"player_id":1150276670},{"rank":40,"player_name":"LEEEGEENDARYYY","rank_name":"Grandmaster 1","score":4750,"matches":60,"player_id":1306026005},{"rank":41,"player_name":"JuC3","rank_name":"Grandmaster 1","score":4743,"matches":84,"player_id":1276068088},{"rank":42,"player_name":"VivaLaTaper","rank_name":"Grandmaster 1","score":4736,"matches":77,"player_id":427352189},{"rank":43,"player_name":"NearN1","rank_name":"Grandmaster 1","score":4734,"matches":51,"player_id":665268357},{"rank":44,"player_name":"GoyPlayingMR","rank_name":"Grandmaster 1","score":4727,"matches":61,"player_id":1136410458},{"rank":45,"player_name":"vgchamp1","rank_name":"Grandmaster 1","score":4725,"matches":66,"player_id":1856573843},{"rank":46,"player_name":"RonySize","rank_name":"Grandmaster 1","score":4723,"matches":62,"player_id":1144886809},{"rank":47,"player_name":"Larch ツ","rank_name":"Grandmaster 1","score":4714,"matches":77,"player_id":1903647169},{"rank":48,"player_name":"KnF Turbo","rank_name":"Grandmaster 1","score":4713,"matches":155,"player_id":1532817429},{"rank":49,"player_name":"smurfetico1337","rank_name":"Grandmaster 1","score":4704,"matches":190,"player_id":608448028},{"rank":50,"player_name":"pommchamp","rank_name":"Grandmaster 1","score":4699,"matches":53,"player_id":1318678338},{"rank":51,"player_name":"Wulfan","rank_name":"Grandmaster 2","score":4697,"matches":76,"player_id":334415147},{"rank":52,"player_name":"91xuc8F","rank_name":"Grandmaster 1","score":4696,"matches":61,"player_id":114739356},{"rank":53,"player_name":"Canadian Hero","rank_name":"Grandmaster 1","score":4693,"matches":55,"player_id":48895174},{"rank":54,"player_name":"hedlund1","rank_name":"Grandmaster 2","score":4691,"matches":79,"player_id":204790184},{"rank":55,"player_name":"Arcneex","rank_name":"Grandmaster 2","score":4687,"matches":72,"player_id":1093582387},{"rank":56,"player_name":"rodor228","rank_name":"Grandmaster 1","score":4685,"matches":497,"player_id":683742412},{"rank":57,"player_name":"darty deedsu","rank_name":"Grandmaster 2","score":4669,"matches":140,"player_id":2015318732},{"rank":58,"player_name":"QKSP","rank_name":"Grandmaster 2","score":4668,"matches":174,"player_id":1685054737},{"rank":59,"player_name":"Penisaurous","rank_name":"Grandmaster 2","score":4667,"matches":87,"player_id":36896737},{"rank":60,"player_name":"Yos2","rank_name":"Grandmaster 2","score":4660,"matches":55,"player_id":699156902},{"rank":61,"player_name":"WarMachine1112","rank_name":"Grandmaster 2","score":4658,"matches":65,"player_id":798520727},{"rank":62,"player_name":"JetStream","rank_name":"Grandmaster 2","score":4655,"matches":247,"player_id":337343511},{"rank":63,"player_name":"trickstus","rank_name":"Grandmaster 2","score":4647,"matches":77,"player_id":303575040},{"rank":64,"player_name":"WanderingSmurf","rank_name":"Grandmaster 2","score":4645,"matches":52,"player_id":1543914894},{"rank":65,"player_name":"lmkcardin","rank_name":"Grandmaster 2","score":4645,"matches":187,"player_id":398930874},{"rank":66,"player_name":"KyleNewin","rank_name":"Grandmaster 2","score":4641,"matches":97,"player_id":1605883434},{"rank":67,"player_name":"Iron man Thor","rank_name":"Grandmaster 2","score":4641,"matches":99,"player_id":1710469657},{"rank":68,"player_name":"zVon","rank_name":"Grandmaster 2","score":4621,"matches":72,"player_id":1681652032},{"rank":69,"player_name":"GabeOW","rank_name":"Grandmaster 2","score":4620,"matches":62,"player_id":1262765690},{"rank":70,"player_name":"Acherons","rank_name":"Grandmaster 2","score":4618,"matches":58,"player_id":759096770},{"rank":71,"player_name":"SLQB","rank_name":"Grandmaster 2","score":4609,"matches":121,"player_id":179686275},{"rank":72,"player_name":"Kazum4","rank_name":"Grandmaster 2","score":4609,"matches":56,"player_id":1183185379},{"rank":73,"player_name":"CarryPoliPoli","rank_name":"Grandmaster 2","score":4603,"matches":78,"player_id":2146104753},{"rank":74,"player_name":"Jinn_07","rank_name":"Grandmaster 2","score":4600,"matches":121,"player_id":596822720},{"rank":75,"player_name":"exe","rank_name":"Grandmaster 2","score":4600,"matches":56,"player_id":1610234753},{"rank":76,"player_name":"HUNK_NA","rank_name":"Grandmaster 2","score":4599,"matches":63,"player_id":344256680},{"rank":77,"player_name":"XLspirit","rank_name":"Grandmaster 2","score":4592,"matches":100,"player_id":629598654},{"rank":78,"player_name":"keimbel","rank_name":"Grandmaster 2","score":4591,"matches":129,"player_id":753358225},{"rank":79,"player_name":"Lahlid","rank_name":"Grandmaster 2","score":4590,"matches":222,"player_id":1340595809},{"rank":80,"player_name":"30secondtomars","rank_name":"Grandmaster 2","score":4588,"matches":261,"player_id":1498715725},{"rank":81,"player_name":"IAmTheLich","rank_name":"Grandmaster 3","score":4586,"matches":99,"player_id":1776150764},{"rank":82,"player_name":"Griffith 52","rank_name":"Grandmaster 2","score":4585,"matches":61,"player_id":964229540},{"rank":83,"player_name":"Funky Monke","rank_name":"Grandmaster 2","score":4582,"matches":56,"player_id":1080045133},{"rank":84,"player_name":"Fitrah","rank_name":"Grandmaster 3","score":4581,"matches":79,"player_id":319231020},{"rank":85,"player_name":"satsu...","rank_name":"Grandmaster 2","score":4581,"matches":99,"player_id":1242346537},{"rank":86,"player_name":"Nirusen","rank_name":"Grandmaster 2","score":4579,"matches":81,"player_id":1951665918},{"rank":87,"player_name":"IGOR05_99","rank_name":"Grandmaster 2","score":4575,"matches":136,"player_id":994884427},{"rank":88,"player_name":"GamerGoose389","rank_name":"Grandmaster 2","score":4574,"matches":55,"player_id":1828282287},{"rank":89,"player_name":"zorkkana","rank_name":"Grandmaster 3","score":4564,"matches":76,"player_id":315982958},{"rank":90,"player_name":"MonkeyManReal1","rank_name":"Grandmaster 3","score":4561,"matches":220,"player_id":491390324},{"rank":91,"player_name":"Kopgalos","rank_name":"Grandmaster 3","score":4561,"matches":54,"player_id":486262220},{"rank":92,"player_name":"TTV 7marmo","rank_name":"Grandmaster 3","score":4560,"matches":69,"player_id":1151574743},{"rank":93,"player_name":"sakkexwx","rank_name":"Grandmaster 3","score":4560,"matches":55,"player_id":1463060271},{"rank":94,"player_name":"neverta","rank_name":"Grandmaster 3","score":4557,"matches":93,"player_id":1454578545},{"rank":95,"player_name":"King GreyTTV","rank_name":"Grandmaster 3","score":4556,"matches":89,"player_id":1931285741},{"rank":96,"player_name":"AtlasThirteen","rank_name":"Grandmaster 3","score":4554,"matches":70,"player_id":2011654320},{"rank":97,"player_name":"Pilon Végétal","rank_name":"Grandmaster 3","score":4553,"matches":222,"player_id":710513701},{"rank":98,"player_name":"Chainsawpirate","rank_name":"Grandmaster 3","score":4552,"matches":158,"player_id":798162349},{"rank":99,"player_name":"IceColdCombos","rank_name":"Grandmaster 3","score":4551,"matches":65,"player_id":467067160},{"rank":100,"player_name":"icy_bo","rank_name":"Grandmaster 3","score":4551,"matches":149,"player_id":1803022749},{"rank":101,"player_name":"SPEEDBREAKER_","rank_name":"Grandmaster 3","score":4549,"matches":99,"player_id":648620444},{"rank":102,"player_name":"1900Rugrat","rank_name":"Grandmaster 3","score":4548,"matches":187,"player_id":1182320177},{"rank":103,"player_name":"SheikDaddy","rank_name":"Grandmaster 3","score":4544,"matches":115,"player_id":629153120},{"rank":104,"player_name":"wavecxz228","rank_name":"Grandmaster 3","score":4532,"matches":70,"player_id":751197550},{"rank":105,"player_name":"BEASTAAA","rank_name":"Grandmaster 3","score":4528,"matches":81,"player_id":1447183538},{"rank":106,"player_name":"cashmoney-","rank_name":"Grandmaster 3","score":4526,"matches":130,"player_id":1518684761},{"rank":107,"player_name":"WmbaZ4Q","rank_name":"Grandmaster 3","score":4525,"matches":82,"player_id":869560721},{"rank":108,"player_name":"Elsoushi","rank_name":"Grandmaster 3","score":4524,"matches":137,"player_id":961273525},{"rank":109,"player_name":"listlesszk","rank_name":"Grandmaster 3","score":4524,"matches":89,"player_id":1110244192},{"rank":110,"player_name":"Hnto","rank_name":"Grandmaster 3","score":4524,"matches":54,"player_id":1826753135},{"rank":111,"player_name":"E777","rank_name":"Grandmaster 3","score":4522,"matches":248,"player_id":73258670},{"rank":112,"player_name":"Lagra","rank_name":"Grandmaster 3","score":4519,"matches":77,"player_id":1205175671},{"rank":113,"player_name":"Escape Fr0m OW","rank_name":"Grandmaster 3","score":4519,"matches":52,"player_id":1424069056},{"rank":114,"player_name":"ScarecrowwFTP","rank_name":"Grandmaster 3","score":4519,"matches":60,"player_id":327943583},{"rank":115,"player_name":"Chatakuri","rank_name":"Grandmaster 3","score":4518,"matches":51,"player_id":448657365},{"rank":116,"player_name":"MeleèGod","rank_name":"Grandmaster 3","score":4517,"matches":68,"player_id":1713313823},{"rank":117,"player_name":"monstrixx","rank_name":"Grandmaster 3","score":4517,"matches":81,"player_id":270647088},{"rank":118,"player_name":"Sixxes","rank_name":"Grandmaster 3","score":4516,"matches":53,"player_id":542315470},{"rank":119,"player_name":"Lasor Beam","rank_name":"Grandmaster 3","score":4515,"matches":55,"player_id":1966086053},{"rank":120,"player_name":"cocadust","rank_name":"Grandmaster 3","score":4513,"matches":177,"player_id":1726171444},{"rank":121,"player_name":"SK No Mercy","rank_name":"Grandmaster 3","score":4513,"matches":130,"player_id":1205154026},{"rank":122,"player_name":"Kasdeyaz","rank_name":"Grandmaster 3","score":4513,"matches":103,"player_id":1656198118},{"rank":123,"player_name":"Brain d3ad","rank_name":"Grandmaster 3","score":4511,"matches":73,"player_id":1787293500},{"rank":124,"player_name":"Phantom4drone","rank_name":"Grandmaster 3","score":4510,"matches":93,"player_id":1785869201},{"rank":125,"player_name":"Robsterhui24","rank_name":"Grandmaster 3","score":4509,"matches":55,"player_id":1151029915},{"rank":126,"player_name":"GoodJobBigMan","rank_name":"Grandmaster 3","score":4508,"matches":72,"player_id":191183127},{"rank":127,"player_name":"Joggekr","rank_name":"Grandmaster 3","score":4507,"matches":143,"player_id":1997248388},{"rank":128,"player_name":"ChrisGotHeat23","rank_name":"Grandmaster 3","score":4506,"matches":67,"player_id":2117217383},{"rank":129,"player_name":"MrLngtip","rank_name":"Grandmaster 3","score":4504,"matches":226,"player_id":305102323},{"rank":130,"player_name":"ConscriptSpidr","rank_name":"Grandmaster 3","score":4503,"matches":59,"player_id":423923127},{"rank":131,"player_name":"Cabal","rank_name":"Grandmaster 3","score":4502,"matches":54,"player_id":143823389},{"rank":132,"player_name":"Maityz","rank_name":"Grandmaster 3","score":4501,"matches":56,"player_id":846783142},{"rank":133,"player_name":"tmdeej","rank_name":"Grandmaster 3","score":4500,"matches":83,"player_id":1228816456},{"rank":134,"player_name":"ThorTheyThem","rank_name":"Diamond 1","score":4499,"matches":60,"player_id":359893639},{"rank":135,"player_name":"Kelminator","rank_name":"Grandmaster 3","score":4499,"matches":53,"player_id":702595529},{"rank":136,"player_name":"bossin2005","rank_name":"Grandmaster 3","score":4499,"matches":56,"player_id":215689550},{"rank":137,"player_name":"Caldur's Gate","rank_name":"Grandmaster 3","score":4495,"matches":54,"player_id":1048021395},{"rank":138,"player_name":"破虚妄","rank_name":"Grandmaster 3","score":4494,"matches":51,"player_id":675533121},{"rank":139,"player_name":"Jonaphx","rank_name":"Diamond 1","score":4494,"matches":54,"player_id":472737741},{"rank":140,"player_name":"Lokzmir","rank_name":"Grandmaster 3","score":4493,"matches":66,"player_id":1113771182},{"rank":141,"player_name":"SpecialXBeam","rank_name":"Diamond 1","score":4491,"matches":56,"player_id":1936181872},{"rank":142,"player_name":"Vance MK-II","rank_name":"Grandmaster 3","score":4489,"matches":65,"player_id":1269309807},{"rank":143,"player_name":"Ozrukar","rank_name":"Grandmaster 3","score":4488,"matches":100,"player_id":2017180387},{"rank":144,"player_name":"Stone Nuts","rank_name":"Grandmaster 3","score":4484,"matches":121,"player_id":1846789445},{"rank":145,"player_name":"qyhqnqbi","rank_name":"Grandmaster 3","score":4483,"matches":104,"player_id":552224654},{"rank":146,"player_name":"HastarYoutube","rank_name":"Diamond 1","score":4481,"matches":90,"player_id":1581311662},{"rank":147,"player_name":"FlaggerM","rank_name":"Grandmaster 3","score":4481,"matches":146,"player_id":1215443965},{"rank":148,"player_name":"ABiscool","rank_name":"Diamond 1","score":4481,"matches":106,"player_id":211568238},{"rank":149,"player_name":"ZAGIAS","rank_name":"Grandmaster 3","score":4480,"matches":103,"player_id":1177047576},{"rank":150,"player_name":"MoveMyCar","rank_name":"Diamond 1","score":4478,"matches":67,"player_id":847196577},{"rank":151,"player_name":"ChiefShields","rank_name":"Grandmaster 3","score":4476,"matches":59,"player_id":1881117873},{"rank":152,"player_name":"Afflixn","rank_name":"Diamond 1","score":4475,"matches":91,"player_id":307902457},{"rank":153,"player_name":"yuishii","rank_name":"Grandmaster 3","score":4473,"matches":81,"player_id":1221957457},{"rank":154,"player_name":"Cyrapite","rank_name":"Diamond 1","score":4472,"matches":110,"player_id":197565379},{"rank":155,"player_name":"rooseve1t","rank_name":"Diamond 1","score":4471,"matches":93,"player_id":319137114},{"rank":156,"player_name":"VerZonic","rank_name":"Grandmaster 3","score":4471,"matches":56,"player_id":2099611309},{"rank":157,"player_name":"The Wheezer","rank_name":"Grandmaster 3","score":4470,"matches":102,"player_id":616817643},{"rank":158,"player_name":"gh0st","rank_name":"Diamond 1","score":4469,"matches":86,"player_id":1894001606},{"rank":159,"player_name":"Teegco","rank_name":"Diamond 1","score":4467,"matches":67,"player_id":143361070},{"rank":160,"player_name":"TTV_DDog","rank_name":"Diamond 1","score":4467,"matches":268,"player_id":1803754327},{"rank":161,"player_name":"arty._","rank_name":"Diamond 1","score":4465,"matches":62,"player_id":216213334},{"rank":162,"player_name":"Shinytrousers","rank_name":"Diamond 1","score":4457,"matches":64,"player_id":1296298280},{"rank":163,"player_name":"neighborpls","rank_name":"Diamond 1","score":4454,"matches":63,"player_id":173924471},{"rank":164,"player_name":"BaarMoedrVoedr","rank_name":"Diamond 1","score":4454,"matches":125,"player_id":2107922602},{"rank":165,"player_name":"YBx3","rank_name":"Diamond 1","score":4454,"matches":115,"player_id":726312647},{"rank":166,"player_name":"A2nSensation","rank_name":"Diamond 1","score":4452,"matches":207,"player_id":1233155820},{"rank":167,"player_name":"Temptalking","rank_name":"Diamond 1","score":4451,"matches":64,"player_id":1413844225},{"rank":168,"player_name":"Not ZeroOo","rank_name":"Diamond 1","score":4451,"matches":188,"player_id":1392725437},{"rank":169,"player_name":"MrWestTTV","rank_name":"Diamond 1","score":4450,"matches":194,"player_id":1185739632},{"rank":170,"player_name":"dazombeslayer","rank_name":"Diamond 1","score":4444,"matches":87,"player_id":82385994},{"rank":171,"player_name":"Nde","rank_name":"Diamond 1","score":4443,"matches":53,"player_id":1490593381},{"rank":172,"player_name":"VolticPhantom","rank_name":"Diamond 1","score":4439,"matches":63,"player_id":766355548},{"rank":173,"player_name":"GalosDJ","rank_name":"Diamond 1","score":4437,"matches":106,"player_id":1650586874},{"rank":174,"player_name":"Persias","rank_name":"Diamond 1","score":4435,"matches":88,"player_id":1401238777},{"rank":175,"player_name":"Xendol","rank_name":"Diamond 1","score":4435,"matches":89,"player_id":483256649},{"rank":176,"player_name":"small_shard","rank_name":"Diamond 1","score":4433,"matches":54,"player_id":32548524},{"rank":177,"player_name":"lowdiddler","rank_name":"Diamond 1","score":4433,"matches":67,"player_id":222502459},{"rank":178,"player_name":"PullUpShootin","rank_name":"Diamond 1","score":4432,"matches":51,"player_id":720978224},{"rank":179,"player_name":"Se3fy","rank_name":"Diamond 1","score":4431,"matches":58,"player_id":830834117},{"rank":180,"player_name":"Jaydog108","rank_name":"Diamond 1","score":4428,"matches":58,"player_id":1686222225},{"rank":181,"player_name":"spirit'","rank_name":"Diamond 1","score":4427,"matches":75,"player_id":964174157},{"rank":182,"player_name":"TheGrid1006","rank_name":"Diamond 1","score":4427,"matches":56,"player_id":521838413},{"rank":183,"player_name":"Descö","rank_name":"Diamond 1","score":4425,"matches":79,"player_id":1312610329},{"rank":184,"player_name":"Tatie-Huguette","rank_name":"Diamond 1","score":4425,"matches":92,"player_id":929974272},{"rank":185,"player_name":"Tyn x","rank_name":"Diamond 1","score":4423,"matches":82,"player_id":540135732},{"rank":186,"player_name":"Kwlashots","rank_name":"Diamond 1","score":4422,"matches":97,"player_id":940577896},{"rank":187,"player_name":"NesnahOG","rank_name":"Diamond 1","score":4422,"matches":60,"player_id":296015640},{"rank":188,"player_name":"H2NT3R9","rank_name":"Diamond 1","score":4422,"matches":202,"player_id":774259272},{"rank":189,"player_name":"wetchief","rank_name":"Diamond 1","score":4419,"matches":74,"player_id":719661149},{"rank":190,"player_name":"MelloL","rank_name":"Diamond 1","score":4419,"matches":55,"player_id":2000562644},{"rank":191,"player_name":"UnSpotted","rank_name":"Diamond 1","score":4418,"matches":60,"player_id":1065234337},{"rank":192,"player_name":"QUΙNN","rank_name":"Diamond 1","score":4417,"matches":230,"player_id":445485374},{"rank":193,"player_name":"MageFounderTTV","rank_name":"Diamond 1","score":4417,"matches":193,"player_id":1774764265},{"rank":194,"player_name":"EngulfingSlime","rank_name":"Diamond 1","score":4414,"matches":55,"player_id":1185983710},{"rank":195,"player_name":"Freshwaterツ","rank_name":"Diamond 1","score":4409,"matches":180,"player_id":1773747028},{"rank":196,"player_name":"bobyblanquita","rank_name":"Diamond 1","score":4408,"matches":69,"player_id":1251621685},{"rank":197,"player_name":"Sigma_Gaming52","rank_name":"Diamond 1","score":4408,"matches":227,"player_id":1809641562},{"rank":198,"player_name":"jayls8","rank_name":"Diamond 1","score":4407,"matches":65,"player_id":1138571871},{"rank":199,"player_name":"Scribblerz","rank_name":"Diamond 1","score":4405,"matches":67,"player_id":616295290},{"rank":200,"player_name":"yvr-z","rank_name":"Diamond 1","score":4405,"matches":99,"player_id":1895191751},{"rank":201,"player_name":"TimFromOBlock","rank_name":"Diamond 1","score":4404,"matches":64,"player_id":551539962},{"rank":202,"player_name":"ReZGamehunter","rank_name":"Diamond 1","score":4404,"matches":74,"player_id":1475212967},{"rank":203,"player_name":"StepOnMePsy","rank_name":"Diamond 1","score":4399,"matches":83,"player_id":914899177},{"rank":204,"player_name":"notstealth_","rank_name":"Diamond 1","score":4398,"matches":153,"player_id":587984890},{"rank":205,"player_name":"TTVdriftr_g3","rank_name":"Diamond 2","score":4398,"matches":244,"player_id":288396614},{"rank":206,"player_name":"daddypepa","rank_name":"Diamond 1","score":4397,"matches":142,"player_id":1284011607},{"rank":207,"player_name":"Razzebuseman","rank_name":"Diamond 1","score":4395,"matches":196,"player_id":1067092597},{"rank":208,"player_name":"ckod","rank_name":"Diamond 2","score":4391,"matches":64,"player_id":858217752},{"rank":209,"player_name":"A1ML0CK","rank_name":"Diamond 1","score":4386,"matches":292,"player_id":2006777830},{"rank":210,"player_name":"Seifcc","rank_name":"Diamond 1","score":4382,"matches":60,"player_id":181010191},{"rank":211,"player_name":"allrange","rank_name":"Diamond 1","score":4381,"matches":53,"player_id":341990618},{"rank":212,"player_name":"P1V1mRT1","rank_name":"Diamond 1","score":4380,"matches":61,"player_id":1145163410},{"rank":213,"player_name":"Zork-kw","rank_name":"Diamond 2","score":4373,"matches":57,"player_id":2025041274},{"rank":214,"player_name":"pkmelee","rank_name":"Diamond 2","score":4372,"matches":56,"player_id":829902530},{"rank":215,"player_name":"Smashin","rank_name":"Diamond 2","score":4372,"matches":55,"player_id":83290818},{"rank":216,"player_name":"GenuineBaller","rank_name":"Diamond 1","score":4371,"matches":79,"player_id":836799232},{"rank":217,"player_name":"zoinkai","rank_name":"Diamond 2","score":4371,"matches":88,"player_id":974245134},{"rank":218,"player_name":"SunCorcoran","rank_name":"Diamond 2","score":4367,"matches":114,"player_id":1289390058},{"rank":219,"player_name":"Ax24","rank_name":"Diamond 2","score":4366,"matches":77,"player_id":2079010748},{"rank":220,"player_name":"J.A.R.V.I.Sr34","rank_name":"Diamond 2","score":4365,"matches":86,"player_id":865069763},{"rank":221,"player_name":"TTV_SHALALAKA","rank_name":"Diamond 2","score":4365,"matches":83,"player_id":1680902126},{"rank":222,"player_name":"Siteev","rank_name":"Diamond 2","score":4365,"matches":158,"player_id":50577696},{"rank":223,"player_name":"Doom_hunter","rank_name":"Diamond 2","score":4364,"matches":102,"player_id":1140568996},{"rank":224,"player_name":"IP_Shin","rank_name":"Diamond 2","score":4363,"matches":83,"player_id":473231467},{"rank":225,"player_name":"ZeroNull5","rank_name":"Diamond 2","score":4363,"matches":109,"player_id":632380536},{"rank":226,"player_name":"Yajuuj","rank_name":"Diamond 2","score":4362,"matches":75,"player_id":81503992},{"rank":227,"player_name":"Reciting","rank_name":"Diamond 2","score":4361,"matches":58,"player_id":1142320730},{"rank":228,"player_name":"Megapkmn77","rank_name":"Diamond 2","score":4355,"matches":67,"player_id":326530293},{"rank":229,"player_name":"Geckster","rank_name":"Diamond 2","score":4352,"matches":237,"player_id":845478706},{"rank":230,"player_name":"ChoogaBooga","rank_name":"Diamond 2","score":4348,"matches":62,"player_id":1298167455},{"rank":231,"player_name":"Merlin5488","rank_name":"Diamond 2","score":4345,"matches":72,"player_id":1513513687},{"rank":232,"player_name":"Sterson","rank_name":"Diamond 2","score":4343,"matches":139,"player_id":1023764894},{"rank":233,"player_name":"ChampionGGs","rank_name":"Diamond 2","score":4341,"matches":90,"player_id":1111805462},{"rank":234,"player_name":"Shaduk","rank_name":"Diamond 2","score":4339,"matches":116,"player_id":1644753407},{"rank":235,"player_name":"reptiIe.","rank_name":"Diamond 2","score":4338,"matches":80,"player_id":1032259825},{"rank":236,"player_name":"Fudge73","rank_name":"Diamond 2","score":4335,"matches":58,"player_id":159224075},{"rank":237,"player_name":"Asznee","rank_name":"Diamond 2","score":4334,"matches":94,"player_id":1784094309},{"rank":238,"player_name":"bluiemoon","rank_name":"Diamond 2","score":4332,"matches":80,"player_id":60360964},{"rank":239,"player_name":"JohnYipeeKiYay","rank_name":"Diamond 2","score":4332,"matches":57,"player_id":1206370684},{"rank":240,"player_name":"Cripjaw","rank_name":"Diamond 2","score":4331,"matches":125,"player_id":1303678972},{"rank":241,"player_name":"ipinkies","rank_name":"Diamond 2","score":4328,"matches":57,"player_id":799542696},{"rank":242,"player_name":"KCGuna","rank_name":"Diamond 2","score":4328,"matches":67,"player_id":1913809908},{"rank":243,"player_name":"FlamingTiger31","rank_name":"Diamond 2","score":4324,"matches":54,"player_id":945876033},{"rank":244,"player_name":"Firexf3","rank_name":"Diamond 2","score":4324,"matches":127,"player_id":1698814105},{"rank":245,"player_name":"Brandingdong","rank_name":"Diamond 2","score":4322,"matches":310,"player_id":2006653768},{"rank":246,"player_name":"Once1776","rank_name":"Diamond 2","score":4322,"matches":79,"player_id":1589693563},{"rank":247,"player_name":"SkillmaticK","rank_name":"Diamond 2","score":4319,"matches":111,"player_id":305623930},{"rank":248,"player_name":"HuIkbuster","rank_name":"Diamond 2","score":4318,"matches":180,"player_id":2047494759},{"rank":249,"player_name":"Carthaginian33","rank_name":"Diamond 2","score":4318,"matches":65,"player_id":542116700},{"rank":250,"player_name":"MinimumPulsee","rank_name":"Diamond 2","score":4316,"matches":104,"player_id":1986861832},{"rank":251,"player_name":"Vronathan","rank_name":"Diamond 2","score":4314,"matches":64,"player_id":2129946590},{"rank":252,"player_name":"ADIVENGER","rank_name":"Diamond 2","score":4314,"matches":84,"player_id":129762554},{"rank":253,"player_name":"ANXX","rank_name":"Diamond 2","score":4310,"matches":112,"player_id":743487358},{"rank":254,"player_name":"Jarvis Simp","rank_name":"Diamond 2","score":4310,"matches":89,"player_id":2091369008},{"rank":255,"player_name":"Anthonyontv","rank_name":"Diamond 2","score":4309,"matches":106,"player_id":1876873582},{"rank":256,"player_name":"Thepixsans","rank_name":"Diamond 2","score":4308,"matches":93,"player_id":735916321},{"rank":257,"player_name":"MilkMeSlow","rank_name":"Diamond 2","score":4304,"matches":57,"player_id":2022393766},{"rank":258,"player_name":"__fear__","rank_name":"Diamond 2","score":4304,"matches":92,"player_id":2027973006},{"rank":259,"player_name":"Voli_VEVO","rank_name":"Diamond 2","score":4302,"matches":100,"player_id":1936121389},{"rank":260,"player_name":"fakehuntorious","rank_name":"Diamond 2","score":4302,"matches":185,"player_id":1454205037},{"rank":261,"player_name":"KingJulianDC","rank_name":"Diamond 2","score":4299,"matches":69,"player_id":762327396},{"rank":262,"player_name":"khldy","rank_name":"Diamond 2","score":4297,"matches":121,"player_id":316713787},{"rank":263,"player_name":"zhinoe","rank_name":"Diamond 2","score":4296,"matches":62,"player_id":770402640},{"rank":264,"player_name":"dont4botpls","rank_name":"Diamond 2","score":4295,"matches":133,"player_id":1467637919},{"rank":265,"player_name":"Backspace098","rank_name":"Diamond 2","score":4295,"matches":84,"player_id":1122290089},{"rank":266,"player_name":"Peponcio69","rank_name":"Diamond 2","score":4295,"matches":87,"player_id":1486766226},{"rank":267,"player_name":"T1 Wolf","rank_name":"Diamond 3","score":4294,"matches":104,"player_id":476703636},{"rank":268,"player_name":"ItsHiroh","rank_name":"Diamond 2","score":4290,"matches":69,"player_id":1372953575},{"rank":269,"player_name":"ClipThatShiet","rank_name":"Diamond 2","score":4287,"matches":51,"player_id":1749477820},{"rank":270,"player_name":"Hermes_Hyd","rank_name":"Diamond 2","score":4287,"matches":68,"player_id":301022857},{"rank":271,"player_name":"froguakecros","rank_name":"Diamond 3","score":4286,"matches":55,"player_id":1007077080},{"rank":272,"player_name":"o0fis","rank_name":"Diamond 3","score":4284,"matches":228,"player_id":363738940},{"rank":273,"player_name":"ZOL7_","rank_name":"Diamond 2","score":4284,"matches":66,"player_id":1915360523},{"rank":274,"player_name":"Womec","rank_name":"Diamond 3","score":4284,"matches":52,"player_id":870575396},{"rank":275,"player_name":"JEclipze","rank_name":"Diamond 3","score":4280,"matches":53,"player_id":1790994627},{"rank":276,"player_name":"SinFulHawk TTV","rank_name":"Diamond 2","score":4278,"matches":53,"player_id":145206127},{"rank":277,"player_name":"Woof__","rank_name":"Diamond 3","score":4277,"matches":61,"player_id":1979570400},{"rank":278,"player_name":"LightzYT","rank_name":"Diamond 3","score":4277,"matches":53,"player_id":678275609},{"rank":279,"player_name":"DiddyMau","rank_name":"Diamond 2","score":4277,"matches":86,"player_id":15259431},{"rank":280,"player_name":"butttz","rank_name":"Diamond 3","score":4276,"matches":59,"player_id":516933195},{"rank":281,"player_name":"dizel913","rank_name":"Diamond 3","score":4275,"matches":90,"player_id":1874672066},{"rank":282,"player_name":"BiggumsThicums","rank_name":"Diamond 3","score":4274,"matches":79,"player_id":1059308465},{"rank":283,"player_name":"ThexBest1","rank_name":"Diamond 2","score":4273,"matches":145,"player_id":1461270583},{"rank":284,"player_name":"MadFShadows","rank_name":"Diamond 3","score":4271,"matches":96,"player_id":107011637},{"rank":285,"player_name":"Adauchi","rank_name":"Diamond 3","score":4269,"matches":127,"player_id":1547246687},{"rank":286,"player_name":"Irоn Mаn","rank_name":"Diamond 3","score":4269,"matches":156,"player_id":1243585476},{"rank":287,"player_name":"ORIYAIN","rank_name":"Diamond 3","score":4269,"matches":52,"player_id":665587959},{"rank":288,"player_name":"Tuviee","rank_name":"Diamond 3","score":4269,"matches":55,"player_id":976340605},{"rank":289,"player_name":"RenegadeSlayer","rank_name":"Diamond 3","score":4268,"matches":60,"player_id":58985049},{"rank":290,"player_name":"Whyamisobaddog","rank_name":"Diamond 3","score":4268,"matches":92,"player_id":1557563453},{"rank":291,"player_name":"Sharizard","rank_name":"Diamond 3","score":4267,"matches":117,"player_id":94392499},{"rank":292,"player_name":"LakshayGOD","rank_name":"Diamond 3","score":4266,"matches":80,"player_id":742923391},{"rank":293,"player_name":"NineTaleddog","rank_name":"Diamond 3","score":4265,"matches":113,"player_id":1192196859},{"rank":294,"player_name":"Lynnn-","rank_name":"Diamond 3","score":4265,"matches":76,"player_id":245552185},{"rank":295,"player_name":"i106","rank_name":"Diamond 3","score":4264,"matches":61,"player_id":1954028970},{"rank":296,"player_name":"LimpBizkt","rank_name":"Diamond 3","score":4262,"matches":52,"player_id":1762388429},{"rank":297,"player_name":"Dream Lord","rank_name":"Diamond 3","score":4261,"matches":73,"player_id":358227656},{"rank":298,"player_name":"PhazeisWashed","rank_name":"Diamond 3","score":4257,"matches":71,"player_id":594529785},{"rank":299,"player_name":"-Niru-","rank_name":"Diamond 3","score":4256,"matches":52,"player_id":2020516680},{"rank":300,"player_name":"nettspendchina","rank_name":"Diamond 3","score":4256,"matches":57,"player_id":154937542},{"rank":301,"player_name":"huntiris","rank_name":"Diamond 3","score":4255,"matches":160,"player_id":1662647296},{"rank":302,"player_name":"Slickius","rank_name":"Diamond 3","score":4254,"matches":74,"player_id":891819797},{"rank":303,"player_name":"crazyboie778","rank_name":"Diamond 3","score":4254,"matches":71,"player_id":146292677},{"rank":304,"player_name":"Ichessepopel","rank_name":"Diamond 3","score":4251,"matches":73,"player_id":437618778},{"rank":305,"player_name":"kamiofthewest","rank_name":"Diamond 3","score":4247,"matches":65,"player_id":1630672422},{"rank":306,"player_name":"yordleweed","rank_name":"Diamond 3","score":4243,"matches":166,"player_id":920086622},{"rank":307,"player_name":"SignalSiege","rank_name":"Diamond 3","score":4240,"matches":65,"player_id":566950012},{"rank":308,"player_name":"Splashh","rank_name":"Diamond 3","score":4240,"matches":54,"player_id":1669905321},{"rank":309,"player_name":"Dontbanme","rank_name":"Diamond 3","score":4240,"matches":72,"player_id":1735049331},{"rank":310,"player_name":"Fekah69","rank_name":"Diamond 3","score":4239,"matches":157,"player_id":937488507},{"rank":311,"player_name":"Joltze","rank_name":"Diamond 3","score":4236,"matches":65,"player_id":455732012},{"rank":312,"player_name":"NXCloudyTwitch","rank_name":"Diamond 3","score":4231,"matches":181,"player_id":1033079638},{"rank":313,"player_name":"E10Sharp","rank_name":"Diamond 3","score":4228,"matches":56,"player_id":670719986},{"rank":314,"player_name":"Hernekeitto","rank_name":"Diamond 3","score":4227,"matches":173,"player_id":1023255986},{"rank":315,"player_name":"GDawg915","rank_name":"Diamond 3","score":4225,"matches":63,"player_id":1642127667},{"rank":316,"player_name":"R3no14","rank_name":"Diamond 3","score":4223,"matches":92,"player_id":1519707683},{"rank":317,"player_name":"ekqmt","rank_name":"Diamond 3","score":4222,"matches":67,"player_id":1744793313},{"rank":318,"player_name":"WindStyle","rank_name":"Diamond 3","score":4222,"matches":123,"player_id":598096712},{"rank":319,"player_name":"Redoxium","rank_name":"Diamond 3","score":4220,"matches":102,"player_id":1613440888},{"rank":320,"player_name":"ElDorit0","rank_name":"Diamond 3","score":4220,"matches":89,"player_id":1020214249},{"rank":321,"player_name":"The_Geneticist","rank_name":"Diamond 3","score":4219,"matches":83,"player_id":1989532580},{"rank":322,"player_name":"BurnVEVO","rank_name":"Diamond 3","score":4217,"matches":83,"player_id":1246107427},{"rank":323,"player_name":"EG_01ST","rank_name":"Diamond 3","score":4217,"matches":69,"player_id":575240884},{"rank":324,"player_name":"pantapidis","rank_name":"Diamond 3","score":4216,"matches":128,"player_id":1281253719},{"rank":325,"player_name":"CaptainTitus69","rank_name":"Diamond 3","score":4216,"matches":128,"player_id":735474533},{"rank":326,"player_name":"ittihad3mk","rank_name":"Diamond 3","score":4216,"matches":55,"player_id":1026129289},{"rank":327,"player_name":"Irоn Мan","rank_name":"Diamond 3","score":4216,"matches":72,"player_id":837899533},{"rank":328,"player_name":"H1Moon","rank_name":"Diamond 3","score":4215,"matches":88,"player_id":1753173488},{"rank":329,"player_name":"I_r_o_n-m_a_n","rank_name":"Diamond 3","score":4215,"matches":56,"player_id":1539863903},{"rank":330,"player_name":".Brynden.","rank_name":"Diamond 3","score":4214,"matches":60,"player_id":827687345},{"rank":331,"player_name":"GammaTR","rank_name":"Diamond 3","score":4214,"matches":51,"player_id":823082916},{"rank":332,"player_name":"ゞSignal","rank_name":"Diamond 3","score":4213,"matches":122,"player_id":1417460398},{"rank":333,"player_name":"Rob Delaney","rank_name":"Diamond 3","score":4211,"matches":83,"player_id":1936451701},{"rank":334,"player_name":"- Niru -","rank_name":"Diamond 3","score":4210,"matches":51,"player_id":839097960},{"rank":335,"player_name":"Iron Wang","rank_name":"Diamond 3","score":4209,"matches":51,"player_id":1305449424},{"rank":336,"player_name":"D_Sin","rank_name":"Diamond 3","score":4208,"matches":76,"player_id":1828307852},{"rank":337,"player_name":"Sodaayo","rank_name":"Diamond 3","score":4208,"matches":59,"player_id":1665974044},{"rank":338,"player_name":"732","rank_name":"Diamond 3","score":4207,"matches":177,"player_id":1991575144},{"rank":339,"player_name":"Ryuksigma123","rank_name":"Diamond 3","score":4206,"matches":130,"player_id":190027683},{"rank":340,"player_name":"OCIRIUX","rank_name":"Diamond 3","score":4206,"matches":54,"player_id":1529654282},{"rank":341,"player_name":"JaxSpookz","rank_name":"Diamond 3","score":4205,"matches":59,"player_id":2014962689},{"rank":342,"player_name":"Vaughn's Cookd","rank_name":"Diamond 3","score":4203,"matches":55,"player_id":1013982237},{"rank":343,"player_name":"VloneThug3","rank_name":"Diamond 3","score":4201,"matches":57,"player_id":1923189071},{"rank":344,"player_name":"iRoyaltyG","rank_name":"Diamond 3","score":4201,"matches":95,"player_id":1520126086},{"rank":345,"player_name":"gbsn","rank_name":"Diamond 3","score":4200,"matches":63,"player_id":1542638893},{"rank":346,"player_name":"Hidralix","rank_name":"Diamond 3","score":4200,"matches":51,"player_id":1220621598},{"rank":347,"player_name":"elRockyDee","rank_name":"Diamond 3","score":4199,"matches":102,"player_id":301704158},{"rank":348,"player_name":"Dafterous","rank_name":"Diamond 3","score":4199,"matches":93,"player_id":2025496225},{"rank":349,"player_name":"DixieNourmous0","rank_name":"Diamond 3","score":4196,"matches":111,"player_id":461268779},{"rank":350,"player_name":"Bearking","rank_name":"Platinum 1","score":4195,"matches":54,"player_id":1103196529},{"rank":351,"player_name":"ForgedLives","rank_name":"Diamond 3","score":4193,"matches":110,"player_id":1869447148},{"rank":352,"player_name":"NotOsamah288","rank_name":"Platinum 1","score":4189,"matches":86,"player_id":1935941065},{"rank":353,"player_name":"SwallowMyLoad.","rank_name":"Platinum 1","score":4189,"matches":73,"player_id":2026555549},{"rank":354,"player_name":"JarlYama","rank_name":"Diamond 3","score":4188,"matches":51,"player_id":332594388},{"rank":355,"player_name":"Ńîǧǧëř","rank_name":"Diamond 3","score":4187,"matches":58,"player_id":1600079009},{"rank":356,"player_name":"Defortlegend","rank_name":"Diamond 3","score":4185,"matches":74,"player_id":1544893719},{"rank":357,"player_name":"skibidimunter9","rank_name":"Platinum 1","score":4184,"matches":58,"player_id":1150991654},{"rank":358,"player_name":"Æther Lucid","rank_name":"Diamond 3","score":4179,"matches":72,"player_id":321546714},{"rank":359,"player_name":"FiveSiamang","rank_name":"Platinum 1","score":4178,"matches":129,"player_id":1889798148},{"rank":360,"player_name":"brion.","rank_name":"Diamond 3","score":4177,"matches":86,"player_id":2044081898},{"rank":361,"player_name":"PikachuPIKAT","rank_name":"Diamond 3","score":4174,"matches":60,"player_id":1860016168},{"rank":362,"player_name":"JinKage07","rank_name":"Platinum 1","score":4172,"matches":110,"player_id":18608060},{"rank":363,"player_name":"xqDpx","rank_name":"Platinum 1","score":4168,"matches":80,"player_id":1690299620},{"rank":364,"player_name":"Izzyツ","rank_name":"Platinum 1","score":4163,"matches":111,"player_id":1512464748},{"rank":365,"player_name":"SirMrDrGod","rank_name":"Platinum 1","score":4161,"matches":288,"player_id":395644640},{"rank":366,"player_name":"BagBoyBubbaTv","rank_name":"Platinum 1","score":4159,"matches":72,"player_id":151110417},{"rank":367,"player_name":"Deezmeganutz","rank_name":"Platinum 1","score":4158,"matches":56,"player_id":276094587},{"rank":368,"player_name":"Sebast9000","rank_name":"Platinum 1","score":4158,"matches":58,"player_id":1769778943},{"rank":369,"player_name":"Hope死","rank_name":"Platinum 1","score":4156,"matches":53,"player_id":2012904139},{"rank":370,"player_name":"HammerMan42069","rank_name":"Platinum 1","score":4153,"matches":56,"player_id":339014543},{"rank":371,"player_name":"SweetCainMusic","rank_name":"Platinum 1","score":4150,"matches":70,"player_id":1228610899},{"rank":372,"player_name":"SpearingFish","rank_name":"Platinum 1","score":4147,"matches":70,"player_id":137071868},{"rank":373,"player_name":"Mclovinbuns","rank_name":"Platinum 1","score":4147,"matches":54,"player_id":1742312645},{"rank":374,"player_name":"hoonibooni","rank_name":"Platinum 1","score":4145,"matches":62,"player_id":2137012070},{"rank":375,"player_name":"Dolinakokaina","rank_name":"Platinum 1","score":4145,"matches":52,"player_id":108667172},{"rank":376,"player_name":"limefatality","rank_name":"Platinum 1","score":4139,"matches":89,"player_id":215912831},{"rank":377,"player_name":"Oneballz28","rank_name":"Platinum 1","score":4139,"matches":67,"player_id":416804847},{"rank":378,"player_name":"HiRezolution","rank_name":"Platinum 1","score":4136,"matches":55,"player_id":19949060},{"rank":379,"player_name":"VF Watson","rank_name":"Platinum 1","score":4136,"matches":51,"player_id":159844433},{"rank":380,"player_name":"Uberkist","rank_name":"Platinum 1","score":4136,"matches":78,"player_id":1956130035},{"rank":381,"player_name":"idontknow952","rank_name":"Platinum 1","score":4136,"matches":60,"player_id":379631631},{"rank":382,"player_name":".IAmTheMilkMan","rank_name":"Platinum 1","score":4134,"matches":176,"player_id":1747078467},{"rank":383,"player_name":"Darkstar27","rank_name":"Platinum 1","score":4134,"matches":80,"player_id":1854812828},{"rank":384,"player_name":"BubblegumChad","rank_name":"Platinum 1","score":4134,"matches":98,"player_id":862418075},{"rank":385,"player_name":"iNin","rank_name":"Platinum 1","score":4132,"matches":126,"player_id":1954903895},{"rank":386,"player_name":"0yv27PF","rank_name":"Platinum 1","score":4129,"matches":52,"player_id":510487812},{"rank":387,"player_name":"Werewolf53","rank_name":"Platinum 1","score":4129,"matches":78,"player_id":1194063621},{"rank":388,"player_name":"BuffMark","rank_name":"Platinum 1","score":4126,"matches":189,"player_id":591724125},{"rank":389,"player_name":"helpmehelpme","rank_name":"Platinum 1","score":4124,"matches":69,"player_id":918695241},{"rank":390,"player_name":"StillCold","rank_name":"Platinum 1","score":4123,"matches":78,"player_id":413874956},{"rank":391,"player_name":"A Cat in Time","rank_name":"Platinum 1","score":4122,"matches":69,"player_id":1641142943},{"rank":392,"player_name":"LukaDoncicFan","rank_name":"Platinum 1","score":4121,"matches":119,"player_id":1227074969},{"rank":393,"player_name":"AValidU5ername","rank_name":"Platinum 1","score":4118,"matches":60,"player_id":754248196},{"rank":394,"player_name":"laufey-","rank_name":"Platinum 1","score":4118,"matches":61,"player_id":322696144},{"rank":395,"player_name":"ImDaddyCool","rank_name":"Platinum 1","score":4117,"matches":72,"player_id":578738931},{"rank":396,"player_name":"king von21","rank_name":"Platinum 1","score":4116,"matches":91,"player_id":1738152782},{"rank":397,"player_name":"FAHERs","rank_name":"Platinum 1","score":4115,"matches":335,"player_id":2052645270},{"rank":398,"player_name":"Terraminium","rank_name":"Platinum 1","score":4111,"matches":136,"player_id":211356461},{"rank":399,"player_name":"DrNighaShmertz","rank_name":"Platinum 1","score":4110,"matches":133,"player_id":1321790963},{"rank":400,"player_name":"GreyGuacamole","rank_name":"Platinum 1","score":4105,"matches":73,"player_id":2006569276},{"rank":401,"player_name":"G_Black","rank_name":"Platinum 1","score":4105,"matches":145,"player_id":1696797798},{"rank":402,"player_name":"PickleDoc","rank_name":"Platinum 1","score":4104,"matches":59,"player_id":424230665},{"rank":403,"player_name":"brandago","rank_name":"Platinum 1","score":4104,"matches":51,"player_id":1374242157},{"rank":404,"player_name":"Ser Erebus","rank_name":"Platinum 1","score":4104,"matches":62,"player_id":1313848467},{"rank":405,"player_name":"ZankTF","rank_name":"Platinum 1","score":4102,"matches":59,"player_id":1992395570},{"rank":406,"player_name":"RattIrl","rank_name":"Platinum 1","score":4101,"matches":58,"player_id":891338417},{"rank":407,"player_name":"Gyari","rank_name":"Platinum 1","score":4101,"matches":63,"player_id":1501985837},{"rank":408,"player_name":"ohyeahbabyyy","rank_name":"Platinum 1","score":4099,"matches":59,"player_id":1209340565},{"rank":409,"player_name":"Sonzua","rank_name":"Platinum 1","score":4098,"matches":88,"player_id":803710329},{"rank":410,"player_name":"GG.医者watson","rank_name":"Platinum 1","score":4098,"matches":114,"player_id":2028712243},{"rank":411,"player_name":"levle1slime","rank_name":"Platinum 1","score":4097,"matches":53,"player_id":328821050},{"rank":412,"player_name":"Ranni'sToilet","rank_name":"Platinum 1","score":4093,"matches":54,"player_id":69759446},{"rank":413,"player_name":"IamDaddyD","rank_name":"Platinum 2","score":4091,"matches":60,"player_id":1038669409},{"rank":414,"player_name":"xPM96","rank_name":"Platinum 2","score":4091,"matches":230,"player_id":2143204309},{"rank":415,"player_name":"MurTwayn","rank_name":"Platinum 2","score":4090,"matches":80,"player_id":1718173877},{"rank":416,"player_name":"GroinHugger","rank_name":"Platinum 1","score":4089,"matches":79,"player_id":228372742},{"rank":417,"player_name":"ipadmillennial","rank_name":"Platinum 2","score":4086,"matches":51,"player_id":1360190286},{"rank":418,"player_name":"Amadell","rank_name":"Platinum 1","score":4085,"matches":78,"player_id":1175480910},{"rank":419,"player_name":"Kakeem","rank_name":"Platinum 1","score":4085,"matches":74,"player_id":1631987952},{"rank":420,"player_name":"Fetus","rank_name":"Platinum 2","score":4080,"matches":79,"player_id":834985816},{"rank":421,"player_name":"MeTaBrolic","rank_name":"Platinum 1","score":4079,"matches":64,"player_id":2111071331},{"rank":422,"player_name":"KindSpirit","rank_name":"Platinum 2","score":4079,"matches":65,"player_id":385064318},{"rank":423,"player_name":"ChikaParkerman","rank_name":"Platinum 2","score":4079,"matches":80,"player_id":1131528682},{"rank":424,"player_name":"KYZEN_D","rank_name":"Platinum 2","score":4079,"matches":58,"player_id":460409166},{"rank":425,"player_name":"K jammin","rank_name":"Platinum 1","score":4077,"matches":75,"player_id":1895555007},{"rank":426,"player_name":"goatedstatplz","rank_name":"Platinum 2","score":4075,"matches":52,"player_id":457953166},{"rank":427,"player_name":"user_Zed","rank_name":"Platinum 2","score":4075,"matches":83,"player_id":643547277},{"rank":428,"player_name":"OignonFree","rank_name":"Platinum 2","score":4073,"matches":54,"player_id":809306080},{"rank":429,"player_name":"CmdrLee","rank_name":"Platinum 2","score":4071,"matches":77,"player_id":613583149},{"rank":430,"player_name":"endylele","rank_name":"Platinum 2","score":4068,"matches":86,"player_id":1707974056},{"rank":431,"player_name":"Splamma","rank_name":"Platinum 2","score":4068,"matches":102,"player_id":303897135},{"rank":432,"player_name":"bs3YfF9","rank_name":"Platinum 2","score":4068,"matches":59,"player_id":1826435602},{"rank":433,"player_name":"SilverflashII","rank_name":"Platinum 2","score":4064,"matches":70,"player_id":1295898294},{"rank":434,"player_name":"Reapssb201","rank_name":"Platinum 2","score":4063,"matches":129,"player_id":1502862542},{"rank":435,"player_name":"D3Wrapz","rank_name":"Platinum 2","score":4063,"matches":66,"player_id":907501167},{"rank":436,"player_name":"RamboKonanS","rank_name":"Platinum 2","score":4062,"matches":56,"player_id":1363012540},{"rank":437,"player_name":"King lord pat","rank_name":"Platinum 2","score":4060,"matches":130,"player_id":1022451414},{"rank":438,"player_name":"انتهينا","rank_name":"Platinum 2","score":4055,"matches":63,"player_id":937988601},{"rank":439,"player_name":"Freezxy_","rank_name":"Platinum 2","score":4051,"matches":75,"player_id":797180584},{"rank":440,"player_name":"TheEarthisflat","rank_name":"Platinum 2","score":4051,"matches":64,"player_id":3066772},{"rank":441,"player_name":"DrScrimples","rank_name":"Platinum 2","score":4050,"matches":54,"player_id":2018705332},{"rank":442,"player_name":"AyyyCookie","rank_name":"Platinum 2","score":4049,"matches":85,"player_id":1763860334},{"rank":443,"player_name":"yabadabuh","rank_name":"Platinum 2","score":4049,"matches":74,"player_id":263162180},{"rank":444,"player_name":"DIO_OID","rank_name":"Platinum 2","score":4047,"matches":98,"player_id":1375129435},{"rank":445,"player_name":"HESPERION","rank_name":"Platinum 2","score":4047,"matches":93,"player_id":221874634},{"rank":446,"player_name":"M_hernandez4","rank_name":"Platinum 2","score":4047,"matches":230,"player_id":57813705},{"rank":447,"player_name":"FeresWheel","rank_name":"Platinum 2","score":4045,"matches":55,"player_id":850640510},{"rank":448,"player_name":"Woogzies","rank_name":"Platinum 2","score":4045,"matches":51,"player_id":288936321},{"rank":449,"player_name":"Dubbzie","rank_name":"Platinum 2","score":4045,"matches":118,"player_id":847512612},{"rank":450,"player_name":"Harry3c","rank_name":"Platinum 2","score":4045,"matches":53,"player_id":1540885573},{"rank":451,"player_name":"DAVINXI","rank_name":"Platinum 2","score":4044,"matches":102,"player_id":1522015325},{"rank":452,"player_name":"RNPSSWTLFYKAT","rank_name":"Platinum 2","score":4044,"matches":52,"player_id":2042994288},{"rank":453,"player_name":"RakinBlaze","rank_name":"Platinum 2","score":4044,"matches":56,"player_id":879573088},{"rank":454,"player_name":"Pussibilities","rank_name":"Platinum 2","score":4043,"matches":71,"player_id":1283381519},{"rank":455,"player_name":"turko1020","rank_name":"Platinum 2","score":4043,"matches":60,"player_id":2038665716},{"rank":456,"player_name":"JohnMayhem","rank_name":"Platinum 2","score":4042,"matches":113,"player_id":647921535},{"rank":457,"player_name":"SoydraxGM","rank_name":"Platinum 2","score":4039,"matches":78,"player_id":328922856},{"rank":458,"player_name":"RuinoR","rank_name":"Platinum 2","score":4038,"matches":57,"player_id":1324804170},{"rank":459,"player_name":"WatchTae","rank_name":"Platinum 2","score":4037,"matches":57,"player_id":1220855899},{"rank":460,"player_name":"poopyim","rank_name":"Platinum 2","score":4035,"matches":54,"player_id":486295980},{"rank":461,"player_name":"TechnoSn0w95","rank_name":"Platinum 2","score":4033,"matches":61,"player_id":1145988741},{"rank":462,"player_name":"Psycho Syth","rank_name":"Platinum 2","score":4027,"matches":91,"player_id":1456276218},{"rank":463,"player_name":"teatap","rank_name":"Platinum 2","score":4027,"matches":138,"player_id":433371875},{"rank":464,"player_name":"Thomas Liddell","rank_name":"Platinum 2","score":4021,"matches":63,"player_id":1807204710},{"rank":465,"player_name":".Tb","rank_name":"Platinum 2","score":4020,"matches":73,"player_id":1718061859},{"rank":466,"player_name":"himmm.","rank_name":"Platinum 2","score":4020,"matches":219,"player_id":1057619606},{"rank":467,"player_name":"Morphfex","rank_name":"Platinum 2","score":4019,"matches":59,"player_id":687167108},{"rank":468,"player_name":"Lividfanatic4","rank_name":"Platinum 2","score":4018,"matches":65,"player_id":717513117},{"rank":469,"player_name":"OneShotRichTV","rank_name":"Platinum 2","score":4013,"matches":77,"player_id":2139974586},{"rank":470,"player_name":"Oneshot1","rank_name":"Platinum 2","score":4012,"matches":51,"player_id":1559481933},{"rank":471,"player_name":"FlashIsGodly","rank_name":"Platinum 2","score":4006,"matches":51,"player_id":1937452893},{"rank":472,"player_name":"pehzer","rank_name":"Platinum 2","score":4005,"matches":102,"player_id":1582586716},{"rank":473,"player_name":"TravisIsANonce","rank_name":"Platinum 2","score":4005,"matches":63,"player_id":1153115985},{"rank":474,"player_name":"HavocSimulator","rank_name":"Platinum 2","score":4004,"matches":65,"player_id":384617699},{"rank":475,"player_name":"peanutbrain96","rank_name":"Platinum 2","score":4003,"matches":130,"player_id":1567484507},{"rank":476,"player_name":"Neurotropic","rank_name":"Platinum 2","score":4001,"matches":69,"player_id":726042240},{"rank":477,"player_name":"sherlok123","rank_name":"Platinum 2","score":3999,"matches":62,"player_id":1777685592},{"rank":478,"player_name":"Jxce1","rank_name":"Platinum 3","score":3999,"matches":60,"player_id":438590782},{"rank":479,"player_name":"Steeper.HL","rank_name":"Platinum 2","score":3997,"matches":90,"player_id":1570560674},{"rank":480,"player_name":"Spirit_Drive","rank_name":"Platinum 2","score":3994,"matches":248,"player_id":171474876},{"rank":481,"player_name":"CajunWiseguy","rank_name":"Platinum 2","score":3993,"matches":68,"player_id":1301138142},{"rank":482,"player_name":"huhwhowhy","rank_name":"Platinum 2","score":3993,"matches":159,"player_id":159398466},{"rank":483,"player_name":"Bricccck","rank_name":"Platinum 3","score":3989,"matches":78,"player_id":1429576163},{"rank":484,"player_name":"Figaro4ever","rank_name":"Platinum 3","score":3984,"matches":70,"player_id":522126788},{"rank":485,"player_name":"Bunyskrt","rank_name":"Platinum 3","score":3983,"matches":189,"player_id":657712509},{"rank":486,"player_name":"foundmary","rank_name":"Platinum 3","score":3982,"matches":57,"player_id":1704103936},{"rank":487,"player_name":"Legendaaaaa","rank_name":"Platinum 2","score":3982,"matches":97,"player_id":676890382},{"rank":488,"player_name":"The Pixel","rank_name":"Platinum 2","score":3981,"matches":137,"player_id":587724333},{"rank":489,"player_name":"oilb","rank_name":"Platinum 2","score":3980,"matches":53,"player_id":320646561},{"rank":490,"player_name":"BBCSiam","rank_name":"Platinum 3","score":3979,"matches":64,"player_id":1083952124},{"rank":491,"player_name":"funksti","rank_name":"Platinum 3","score":3975,"matches":92,"player_id":406880472},{"rank":492,"player_name":"SuperRpx","rank_name":"Platinum 2","score":3974,"matches":56,"player_id":1571673446},{"rank":493,"player_name":"Loland0ff","rank_name":"Platinum 3","score":3968,"matches":52,"player_id":205610378},{"rank":494,"player_name":"Windknight196","rank_name":"Platinum 3","score":3968,"matches":71,"player_id":1962924411},{"rank":495,"player_name":"00J2NX00","rank_name":"Platinum 3","score":3967,"matches":68,"player_id":987388430},{"rank":496,"player_name":"KongenavNorge","rank_name":"Platinum 3","score":3967,"matches":116,"player_id":357270264},{"rank":497,"player_name":"mxrah10","rank_name":"Platinum 3","score":3966,"matches":98,"player_id":2009318875},{"rank":498,"player_name":"PikaPikaVT","rank_name":"Platinum 3","score":3965,"matches":88,"player_id":1866715940},{"rank":499,"player_name":"mickasy","rank_name":"Platinum 3","score":3965,"matches":83,"player_id":774759314},{"rank":500,"player_name":"_ENERGY_","rank_name":"Platinum 3","score":3965,"matches":64,"player_id":2063153409}]