[{"rank":1,"player_name":"EatingPizzaRn","rank_name":"One Above All","score":5518,"matches":89,"player_id":928830983},{"rank":2,"player_name":"nx >_<","rank_name":"One Above All","score":5506,"matches":193,"player_id":1632463162},{"rank":3,"player_name":"MCHOOOOOOPER","rank_name":"One Above All","score":5410,"matches":58,"player_id":1197495745},{"rank":4,"player_name":"cosmicnx","rank_name":"One Above All","score":5387,"matches":164,"player_id":937931958},{"rank":5,"player_name":"s1natraa","rank_name":"One Above All","score":5382,"matches":61,"player_id":644692211},{"rank":6,"player_name":"speedily","rank_name":"One Above All","score":5371,"matches":89,"player_id":1677216165},{"rank":7,"player_name":"Monotone","rank_name":"One Above All","score":5358,"matches":69,"player_id":463968516},{"rank":8,"player_name":"happy23","rank_name":"One Above All","score":5345,"matches":64,"player_id":1378438778},{"rank":9,"player_name":"Neko","rank_name":"One Above All","score":5343,"matches":62,"player_id":754556306},{"rank":10,"player_name":"33Heavens","rank_name":"One Above All","score":5343,"matches":202,"player_id":497105475},{"rank":11,"player_name":"SuperGomez","rank_name":"One Above All","score":5337,"matches":62,"player_id":1497053768},{"rank":12,"player_name":"stravery","rank_name":"One Above All","score":5335,"matches":196,"player_id":1263678808},{"rank":13,"player_name":"Etoᅟ","rank_name":"One Above All","score":5321,"matches":91,"player_id":901014277},{"rank":14,"player_name":"CRASH_-","rank_name":"One Above All","score":5306,"matches":80,"player_id":1809010480},{"rank":15,"player_name":"mhd","rank_name":"One Above All","score":5305,"matches":89,"player_id":1839364841},{"rank":16,"player_name":"LewNotSerious","rank_name":"Eternity","score":5293,"matches":435,"player_id":871116073},{"rank":17,"player_name":"Jokerrdx","rank_name":"One Above All","score":5291,"matches":128,"player_id":969158409},{"rank":18,"player_name":"wasddddd","rank_name":"One Above All","score":5290,"matches":76,"player_id":2130839696},{"rank":19,"player_name":"GodWasReal","rank_name":"One Above All","score":5274,"matches":228,"player_id":1901822932},{"rank":20,"player_name":"THANOS2007","rank_name":"One Above All","score":5272,"matches":99,"player_id":2027952738},{"rank":21,"player_name":"m4rch","rank_name":"Eternity","score":5241,"matches":139,"player_id":1622743987},{"rank":22,"player_name":"Zelah","rank_name":"Eternity","score":5236,"matches":174,"player_id":27113035},{"rank":23,"player_name":"penguin0000000","rank_name":"Eternity","score":5234,"matches":55,"player_id":1187383886},{"rank":24,"player_name":"domaltantavuk","rank_name":"Eternity","score":5234,"matches":71,"player_id":979583861},{"rank":25,"player_name":"lanreK","rank_name":"Eternity","score":5230,"matches":114,"player_id":296630068},{"rank":26,"player_name":"vexaur","rank_name":"Eternity","score":5224,"matches":71,"player_id":1046057794},{"rank":27,"player_name":"rоѕе","rank_name":"Eternity","score":5222,"matches":77,"player_id":1793278800},{"rank":28,"player_name":"Tero_TTV","rank_name":"Eternity","score":5212,"matches":61,"player_id":573532488},{"rank":29,"player_name":"steadyFPS.","rank_name":"Eternity","score":5206,"matches":58,"player_id":1439496407},{"rank":30,"player_name":"SlurSorcerer","rank_name":"Eternity","score":5198,"matches":166,"player_id":948613658},{"rank":31,"player_name":"twitchLanderr1","rank_name":"Eternity","score":5198,"matches":146,"player_id":499745711},{"rank":32,"player_name":"Prillist","rank_name":"Eternity","score":5198,"matches":92,"player_id":1480246104},{"rank":33,"player_name":"dt.","rank_name":"Eternity","score":5195,"matches":144,"player_id":648756222},{"rank":34,"player_name":"zombie12thfan","rank_name":"Eternity","score":5190,"matches":172,"player_id":2106030823},{"rank":35,"player_name":"Slaes","rank_name":"Eternity","score":5185,"matches":226,"player_id":1029677128},{"rank":36,"player_name":"2018uzi","rank_name":"Eternity","score":5185,"matches":121,"player_id":159263494},{"rank":37,"player_name":"kats","rank_name":"Eternity","score":5184,"matches":94,"player_id":970948912},{"rank":38,"player_name":"Nitrao","rank_name":"Eternity","score":5184,"matches":51,"player_id":1454979490},{"rank":39,"player_name":"olegattoor TTV","rank_name":"One Above All","score":5181,"matches":76,"player_id":7307269},{"rank":40,"player_name":"Easy Q","rank_name":"One Above All","score":5180,"matches":139,"player_id":247844181},{"rank":41,"player_name":"happy2","rank_name":"Eternity","score":5176,"matches":131,"player_id":106197472},{"rank":42,"player_name":"rib","rank_name":"Eternity","score":5174,"matches":133,"player_id":647020660},{"rank":43,"player_name":"Stirdu","rank_name":"Eternity","score":5168,"matches":174,"player_id":1732478009},{"rank":44,"player_name":"seta_aki","rank_name":"Eternity","score":5165,"matches":211,"player_id":1098706905},{"rank":45,"player_name":"Jur3ky_","rank_name":"Eternity","score":5165,"matches":234,"player_id":607130572},{"rank":46,"player_name":"schlonk","rank_name":"Eternity","score":5165,"matches":99,"player_id":572441386},{"rank":47,"player_name":"<3wonyoung","rank_name":"Eternity","score":5164,"matches":76,"player_id":623569343},{"rank":48,"player_name":"un1_fpsTTV","rank_name":"One Above All","score":5162,"matches":157,"player_id":894183638},{"rank":49,"player_name":"Kehnys","rank_name":"Eternity","score":5162,"matches":51,"player_id":917875476},{"rank":50,"player_name":"P_tatoGG","rank_name":"Eternity","score":5160,"matches":104,"player_id":655407641},{"rank":51,"player_name":"Legit_Kachow","rank_name":"Eternity","score":5158,"matches":155,"player_id":1173295014},{"rank":52,"player_name":"Unleashed","rank_name":"Eternity","score":5155,"matches":182,"player_id":2075395843},{"rank":53,"player_name":"sillycatboyy","rank_name":"Eternity","score":5155,"matches":194,"player_id":1729863075},{"rank":54,"player_name":"CRaZy1329","rank_name":"Eternity","score":5151,"matches":98,"player_id":1327420219},{"rank":55,"player_name":"ur not thanos","rank_name":"Eternity","score":5151,"matches":63,"player_id":1411277985},{"rank":56,"player_name":"PrimeSQ","rank_name":"One Above All","score":5138,"matches":54,"player_id":51086919},{"rank":57,"player_name":"Sestroyed","rank_name":"Eternity","score":5133,"matches":58,"player_id":752834376},{"rank":58,"player_name":"1ndebt","rank_name":"Eternity","score":5131,"matches":82,"player_id":168546942},{"rank":59,"player_name":"Itz_Kenji","rank_name":"Eternity","score":5123,"matches":110,"player_id":1311758189},{"rank":60,"player_name":"postfps","rank_name":"Eternity","score":5117,"matches":142,"player_id":766088396},{"rank":61,"player_name":"lilraxx","rank_name":"Eternity","score":5115,"matches":141,"player_id":212306358},{"rank":62,"player_name":"SuddenOVERWATC","rank_name":"Eternity","score":5114,"matches":213,"player_id":407074003},{"rank":63,"player_name":"radarglimpse","rank_name":"Eternity","score":5112,"matches":139,"player_id":536762465},{"rank":64,"player_name":"baaknuts","rank_name":"Eternity","score":5110,"matches":55,"player_id":238994032},{"rank":65,"player_name":"genjiotp","rank_name":"Eternity","score":5110,"matches":100,"player_id":2129806105},{"rank":66,"player_name":"Lexphen","rank_name":"Eternity","score":5104,"matches":416,"player_id":1875023146},{"rank":67,"player_name":"Ѕаul","rank_name":"Eternity","score":5103,"matches":54,"player_id":169486777},{"rank":68,"player_name":"ORIFRI","rank_name":"Eternity","score":5101,"matches":212,"player_id":624488661},{"rank":69,"player_name":"Rigsychu","rank_name":"Eternity","score":5101,"matches":150,"player_id":1345579222},{"rank":70,"player_name":"brookss","rank_name":"Eternity","score":5101,"matches":170,"player_id":1768083603},{"rank":71,"player_name":"Jackomonster","rank_name":"Eternity","score":5100,"matches":230,"player_id":202305470},{"rank":72,"player_name":"MUSIC2025","rank_name":"Eternity","score":5098,"matches":118,"player_id":2008407306},{"rank":73,"player_name":"kozy","rank_name":"Eternity","score":5094,"matches":117,"player_id":1008968780},{"rank":74,"player_name":"Sivarn","rank_name":"Celestial 1","score":5093,"matches":62,"player_id":1663676207},{"rank":75,"player_name":"DUMPТY","rank_name":"Eternity","score":5091,"matches":63,"player_id":1151751194},{"rank":76,"player_name":"j0nnyxp","rank_name":"Eternity","score":5091,"matches":135,"player_id":1646079315},{"rank":77,"player_name":"ехalt","rank_name":"Eternity","score":5086,"matches":127,"player_id":710329137},{"rank":78,"player_name":"NoraFawn..","rank_name":"Celestial 1","score":5084,"matches":175,"player_id":382877959},{"rank":79,"player_name":"thehappygamer","rank_name":"Eternity","score":5079,"matches":81,"player_id":700670999},{"rank":80,"player_name":"Amatsuki","rank_name":"Celestial 1","score":5076,"matches":488,"player_id":621706867},{"rank":81,"player_name":"Rusһ","rank_name":"Celestial 1","score":5071,"matches":68,"player_id":1465352632},{"rank":82,"player_name":"Prison Rules","rank_name":"Celestial 1","score":5065,"matches":591,"player_id":1551272204},{"rank":83,"player_name":"stupid marmot","rank_name":"Celestial 1","score":5062,"matches":59,"player_id":315104893},{"rank":84,"player_name":"ryguz","rank_name":"Celestial 1","score":5059,"matches":88,"player_id":295277280},{"rank":85,"player_name":"ImDSU","rank_name":"Celestial 1","score":5058,"matches":170,"player_id":1186551899},{"rank":86,"player_name":"Breinholt","rank_name":"Celestial 1","score":5057,"matches":78,"player_id":1088212826},{"rank":87,"player_name":"JeffDays","rank_name":"Celestial 1","score":5053,"matches":101,"player_id":31898238},{"rank":88,"player_name":"DanSlays","rank_name":"Celestial 1","score":5053,"matches":101,"player_id":1386507442},{"rank":89,"player_name":"SUPPRESSTTV","rank_name":"Celestial 1","score":5049,"matches":86,"player_id":1221058723},{"rank":90,"player_name":"pokv","rank_name":"Celestial 1","score":5042,"matches":296,"player_id":987717933},{"rank":91,"player_name":"feedbackr","rank_name":"Celestial 1","score":5037,"matches":110,"player_id":1563599828},{"rank":92,"player_name":"Cxse","rank_name":"Celestial 1","score":5036,"matches":123,"player_id":759098304},{"rank":93,"player_name":"GODMOBA","rank_name":"Celestial 1","score":5035,"matches":81,"player_id":714103229},{"rank":94,"player_name":"Zerdrick","rank_name":"Celestial 1","score":5035,"matches":54,"player_id":2009127014},{"rank":95,"player_name":"Jay3","rank_name":"Celestial 1","score":5035,"matches":82,"player_id":858980387},{"rank":96,"player_name":"Ninjune","rank_name":"Celestial 1","score":5034,"matches":58,"player_id":889757316},{"rank":97,"player_name":"8kj","rank_name":"Celestial 1","score":5033,"matches":80,"player_id":423549875},{"rank":98,"player_name":"Dragoŋ","rank_name":"Celestial 1","score":5032,"matches":342,"player_id":1915091234},{"rank":99,"player_name":"oD Adderall","rank_name":"Celestial 1","score":5031,"matches":118,"player_id":226250411},{"rank":100,"player_name":"・bliss3three","rank_name":"Celestial 1","score":5030,"matches":88,"player_id":420013911},{"rank":101,"player_name":"wbat","rank_name":"Celestial 1","score":5027,"matches":113,"player_id":1706763588},{"rank":102,"player_name":"slvvr","rank_name":"Celestial 1","score":5026,"matches":86,"player_id":262713105},{"rank":103,"player_name":"JoeeOT","rank_name":"Celestial 1","score":5025,"matches":104,"player_id":1451983189},{"rank":104,"player_name":"dnop","rank_name":"Celestial 1","score":5023,"matches":71,"player_id":481453637},{"rank":105,"player_name":"Difference_","rank_name":"Celestial 1","score":5022,"matches":78,"player_id":1180659830},{"rank":106,"player_name":"MedicLmao","rank_name":"Celestial 1","score":5018,"matches":88,"player_id":917302743},{"rank":107,"player_name":"WigglyWombat29","rank_name":"Celestial 1","score":5017,"matches":125,"player_id":393751275},{"rank":108,"player_name":"dylana","rank_name":"Celestial 1","score":5017,"matches":110,"player_id":1022983298},{"rank":109,"player_name":"Luriku","rank_name":"Celestial 1","score":5015,"matches":121,"player_id":2014947134},{"rank":110,"player_name":"Pajko","rank_name":"Celestial 1","score":5010,"matches":235,"player_id":859259418},{"rank":111,"player_name":"meandgranny","rank_name":"Celestial 1","score":5010,"matches":170,"player_id":951546960},{"rank":112,"player_name":"Khan1","rank_name":"Celestial 1","score":5010,"matches":191,"player_id":628205246},{"rank":113,"player_name":"ezagdne","rank_name":"Celestial 1","score":5009,"matches":117,"player_id":1866597556},{"rank":114,"player_name":"forсe","rank_name":"Celestial 1","score":5007,"matches":614,"player_id":231206487},{"rank":115,"player_name":"BootyScratcher","rank_name":"Celestial 1","score":5005,"matches":98,"player_id":1950051553},{"rank":116,"player_name":"WhoElseButBagg","rank_name":"Celestial 1","score":5005,"matches":388,"player_id":528825970},{"rank":117,"player_name":"111FRIEREN","rank_name":"Celestial 1","score":5004,"matches":78,"player_id":1964123006},{"rank":118,"player_name":"iseraaph","rank_name":"Celestial 1","score":5004,"matches":60,"player_id":1036907094},{"rank":119,"player_name":"Not hugE","rank_name":"Celestial 1","score":5003,"matches":53,"player_id":942177617},{"rank":120,"player_name":"littlesoul","rank_name":"Celestial 1","score":5003,"matches":603,"player_id":850905087},{"rank":121,"player_name":"F3zyX","rank_name":"Celestial 1","score":5003,"matches":52,"player_id":1723700551},{"rank":122,"player_name":"Prime Xis","rank_name":"Celestial 1","score":5001,"matches":179,"player_id":2075790710},{"rank":123,"player_name":"MegaNutL1cker","rank_name":"Celestial 1","score":5001,"matches":84,"player_id":832969007},{"rank":124,"player_name":"hitscan slave","rank_name":"Celestial 1","score":5001,"matches":206,"player_id":1968052470},{"rank":125,"player_name":"LonnieQpTWITCH","rank_name":"Celestial 1","score":5001,"matches":124,"player_id":1610457405},{"rank":126,"player_name":"snie","rank_name":"Celestial 1","score":5000,"matches":119,"player_id":451045825},{"rank":127,"player_name":"el griefo","rank_name":"Celestial 1","score":4992,"matches":67,"player_id":650240282},{"rank":128,"player_name":"P_ixh","rank_name":"Celestial 1","score":4990,"matches":424,"player_id":1329385160},{"rank":129,"player_name":"OscarTheWizard","rank_name":"Celestial 2","score":4989,"matches":123,"player_id":110030477},{"rank":130,"player_name":"JaxenJ","rank_name":"Celestial 1","score":4986,"matches":54,"player_id":1818593715},{"rank":131,"player_name":"GetCharged","rank_name":"Celestial 1","score":4985,"matches":141,"player_id":1127936031},{"rank":132,"player_name":"MADLITMIKE33","rank_name":"Celestial 2","score":4985,"matches":117,"player_id":459813206},{"rank":133,"player_name":"Zorrn","rank_name":"Celestial 1","score":4982,"matches":92,"player_id":1246853809},{"rank":134,"player_name":"Pigboyy","rank_name":"Celestial 2","score":4979,"matches":294,"player_id":961340451},{"rank":135,"player_name":"Cehvi","rank_name":"Celestial 1","score":4979,"matches":78,"player_id":1894209734},{"rank":136,"player_name":"Peeckles","rank_name":"Celestial 2","score":4979,"matches":53,"player_id":172941110},{"rank":137,"player_name":"Zuruuuu","rank_name":"Celestial 2","score":4978,"matches":65,"player_id":836527229},{"rank":138,"player_name":"hyunn","rank_name":"Celestial 2","score":4977,"matches":51,"player_id":1838590066},{"rank":139,"player_name":"Doreedo","rank_name":"Celestial 2","score":4976,"matches":62,"player_id":594742670},{"rank":140,"player_name":"ruinw","rank_name":"Celestial 2","score":4974,"matches":61,"player_id":870412969},{"rank":141,"player_name":"nyх","rank_name":"Celestial 1","score":4973,"matches":326,"player_id":1382023200},{"rank":142,"player_name":"hoinked","rank_name":"Celestial 2","score":4969,"matches":111,"player_id":1926605713},{"rank":143,"player_name":"wockypocky","rank_name":"Celestial 2","score":4968,"matches":83,"player_id":502402081},{"rank":144,"player_name":"pierce40","rank_name":"Celestial 2","score":4967,"matches":173,"player_id":1523664948},{"rank":145,"player_name":"enomese","rank_name":"Celestial 2","score":4967,"matches":95,"player_id":1099374403},{"rank":146,"player_name":"ZanCryw","rank_name":"Celestial 2","score":4966,"matches":237,"player_id":415301695},{"rank":147,"player_name":"FrozenNQ","rank_name":"Celestial 2","score":4966,"matches":95,"player_id":1300918882},{"rank":148,"player_name":"cucubaus","rank_name":"Celestial 2","score":4965,"matches":161,"player_id":1560445227},{"rank":149,"player_name":"RiskerFPS","rank_name":"Celestial 2","score":4964,"matches":53,"player_id":44423196},{"rank":150,"player_name":"Squidmaster","rank_name":"Celestial 2","score":4963,"matches":189,"player_id":538104425},{"rank":151,"player_name":"Skyplays101","rank_name":"Celestial 2","score":4962,"matches":130,"player_id":1954692848},{"rank":152,"player_name":"Hqrdest","rank_name":"Celestial 2","score":4960,"matches":131,"player_id":544745888},{"rank":153,"player_name":"Rubithysts","rank_name":"Celestial 2","score":4960,"matches":255,"player_id":1185516994},{"rank":154,"player_name":"Shaxnk","rank_name":"Celestial 2","score":4958,"matches":51,"player_id":848152727},{"rank":155,"player_name":"against","rank_name":"Celestial 2","score":4956,"matches":69,"player_id":1198883599},{"rank":156,"player_name":"SaudiPunk","rank_name":"Celestial 2","score":4954,"matches":86,"player_id":1870804622},{"rank":157,"player_name":"MavisHaHa","rank_name":"Celestial 2","score":4952,"matches":74,"player_id":609230906},{"rank":158,"player_name":"A Tw1nk","rank_name":"Celestial 2","score":4948,"matches":65,"player_id":1272202461},{"rank":159,"player_name":"Pad7","rank_name":"Celestial 2","score":4947,"matches":139,"player_id":861316319},{"rank":160,"player_name":"ELKING7","rank_name":"Celestial 2","score":4936,"matches":74,"player_id":1909554588},{"rank":161,"player_name":"braxy.","rank_name":"Celestial 2","score":4935,"matches":64,"player_id":6857677},{"rank":162,"player_name":"Kyrmi","rank_name":"Celestial 2","score":4932,"matches":55,"player_id":1722267230},{"rank":163,"player_name":"dynsar","rank_name":"Celestial 2","score":4931,"matches":139,"player_id":1594051759},{"rank":164,"player_name":"YOBLAZEE","rank_name":"Celestial 2","score":4928,"matches":76,"player_id":550336510},{"rank":165,"player_name":"Saya__","rank_name":"Celestial 2","score":4928,"matches":96,"player_id":79409308},{"rank":166,"player_name":"Toki_","rank_name":"Celestial 2","score":4926,"matches":74,"player_id":1212597777},{"rank":167,"player_name":"ChrisVA","rank_name":"Celestial 2","score":4925,"matches":99,"player_id":1125894924},{"rank":168,"player_name":"Xalio","rank_name":"Celestial 2","score":4925,"matches":60,"player_id":1559292550},{"rank":169,"player_name":"gzekes","rank_name":"Celestial 2","score":4924,"matches":83,"player_id":1993547855},{"rank":170,"player_name":"MeleeGod","rank_name":"Celestial 2","score":4923,"matches":64,"player_id":1379852980},{"rank":171,"player_name":"Kjimi","rank_name":"Celestial 2","score":4923,"matches":78,"player_id":1095935421},{"rank":172,"player_name":"ItzPerkhs","rank_name":"Celestial 2","score":4922,"matches":91,"player_id":1029838395},{"rank":173,"player_name":"areris","rank_name":"Celestial 2","score":4920,"matches":116,"player_id":845922706},{"rank":174,"player_name":"bpbbc21","rank_name":"Celestial 2","score":4920,"matches":73,"player_id":1125703672},{"rank":175,"player_name":"almost","rank_name":"Celestial 2","score":4918,"matches":220,"player_id":1774991911},{"rank":176,"player_name":"Dough.EXE","rank_name":"Celestial 2","score":4915,"matches":77,"player_id":1763459969},{"rank":177,"player_name":"MrMannerMight","rank_name":"Celestial 2","score":4915,"matches":269,"player_id":323666606},{"rank":178,"player_name":"TTV TotsiMR","rank_name":"Celestial 2","score":4915,"matches":86,"player_id":738487871},{"rank":179,"player_name":"Smiiles.","rank_name":"Celestial 2","score":4914,"matches":86,"player_id":1619950360},{"rank":180,"player_name":"Yeddeongg","rank_name":"Celestial 2","score":4914,"matches":113,"player_id":1792904537},{"rank":181,"player_name":"postlblue","rank_name":"Celestial 2","score":4914,"matches":129,"player_id":1762090963},{"rank":182,"player_name":"Zu..","rank_name":"Celestial 2","score":4912,"matches":68,"player_id":1317977146},{"rank":183,"player_name":"Ethаn","rank_name":"Celestial 2","score":4912,"matches":202,"player_id":1508956164},{"rank":184,"player_name":"Bigmitm","rank_name":"Celestial 2","score":4911,"matches":106,"player_id":174029232},{"rank":185,"player_name":"berryscurry","rank_name":"Celestial 2","score":4911,"matches":54,"player_id":1372782512},{"rank":186,"player_name":"Fresh Soul","rank_name":"Celestial 2","score":4910,"matches":130,"player_id":441084802},{"rank":187,"player_name":"kittenswag2017","rank_name":"Celestial 2","score":4910,"matches":76,"player_id":761178213},{"rank":188,"player_name":"3ye","rank_name":"Celestial 2","score":4909,"matches":106,"player_id":35218919},{"rank":189,"player_name":"NaitsabEN","rank_name":"Celestial 2","score":4909,"matches":200,"player_id":1074191182},{"rank":190,"player_name":"FloydTechAI152","rank_name":"Celestial 2","score":4909,"matches":68,"player_id":2107250549},{"rank":191,"player_name":"1.7.10 potpvp","rank_name":"Celestial 2","score":4907,"matches":300,"player_id":939982924},{"rank":192,"player_name":"sparkythedog2","rank_name":"Celestial 2","score":4907,"matches":52,"player_id":1530099549},{"rank":193,"player_name":"еgoist","rank_name":"Celestial 2","score":4907,"matches":119,"player_id":948846733},{"rank":194,"player_name":"Perfect Egoist","rank_name":"Celestial 2","score":4906,"matches":63,"player_id":1315242065},{"rank":195,"player_name":"TheExo","rank_name":"Celestial 2","score":4903,"matches":64,"player_id":1867400500},{"rank":196,"player_name":"hikobz","rank_name":"Celestial 2","score":4903,"matches":127,"player_id":1231052086},{"rank":197,"player_name":"Yebrir","rank_name":"Celestial 2","score":4902,"matches":101,"player_id":1419422420},{"rank":198,"player_name":"Forrowz","rank_name":"Celestial 2","score":4902,"matches":171,"player_id":736106585},{"rank":199,"player_name":"moistjon","rank_name":"Celestial 2","score":4901,"matches":72,"player_id":2124701499},{"rank":200,"player_name":"gimmethetimmy","rank_name":"Celestial 2","score":4901,"matches":87,"player_id":439115394},{"rank":201,"player_name":"HorrorPeeper","rank_name":"Celestial 2","score":4901,"matches":74,"player_id":1968085226},{"rank":202,"player_name":"stel","rank_name":"Celestial 2","score":4900,"matches":79,"player_id":1779934172},{"rank":203,"player_name":"da1mk0","rank_name":"Celestial 2","score":4899,"matches":92,"player_id":744220405},{"rank":204,"player_name":"immrusty","rank_name":"Celestial 2","score":4899,"matches":72,"player_id":1896168942},{"rank":205,"player_name":"ToonchieTTV","rank_name":"Celestial 2","score":4899,"matches":155,"player_id":278860080},{"rank":206,"player_name":"Biluminaty","rank_name":"Celestial 2","score":4897,"matches":140,"player_id":1707934943},{"rank":207,"player_name":"RosaTzy","rank_name":"Celestial 2","score":4896,"matches":159,"player_id":806298851},{"rank":208,"player_name":"ImMattXD","rank_name":"Celestial 2","score":4895,"matches":90,"player_id":865443652},{"rank":209,"player_name":".Job.","rank_name":"Celestial 2","score":4893,"matches":304,"player_id":498205509},{"rank":210,"player_name":"Alharmoodi","rank_name":"Celestial 3","score":4893,"matches":55,"player_id":2092429399},{"rank":211,"player_name":"DPS Godfather","rank_name":"Celestial 2","score":4891,"matches":85,"player_id":1219266261},{"rank":212,"player_name":"feexzw","rank_name":"Celestial 3","score":4891,"matches":66,"player_id":1340152372},{"rank":213,"player_name":"gun","rank_name":"Celestial 2","score":4889,"matches":179,"player_id":306632560},{"rank":214,"player_name":"Sounes","rank_name":"Celestial 2","score":4889,"matches":90,"player_id":997049830},{"rank":215,"player_name":"zilms","rank_name":"Celestial 2","score":4889,"matches":67,"player_id":1518932102},{"rank":216,"player_name":"SnappyB","rank_name":"Celestial 2","score":4887,"matches":58,"player_id":356085120},{"rank":217,"player_name":"Chan-delure","rank_name":"Celestial 2","score":4887,"matches":91,"player_id":1789439665},{"rank":218,"player_name":"Father Genadii","rank_name":"Celestial 2","score":4887,"matches":160,"player_id":2061902801},{"rank":219,"player_name":"Vedkran","rank_name":"Celestial 2","score":4887,"matches":77,"player_id":348125645},{"rank":220,"player_name":"Electives","rank_name":"Celestial 3","score":4886,"matches":106,"player_id":1393265524},{"rank":221,"player_name":"aFlaker","rank_name":"Celestial 2","score":4884,"matches":151,"player_id":332355577},{"rank":222,"player_name":"IPITYTHEFOOLS","rank_name":"Celestial 3","score":4884,"matches":131,"player_id":1710040492},{"rank":223,"player_name":"R3m1xsz","rank_name":"Celestial 2","score":4884,"matches":73,"player_id":884895105},{"rank":224,"player_name":"Dyfeq","rank_name":"Celestial 3","score":4883,"matches":107,"player_id":1484802459},{"rank":225,"player_name":".yzd","rank_name":"Celestial 2","score":4883,"matches":179,"player_id":1360948387},{"rank":226,"player_name":"Νasty","rank_name":"Celestial 2","score":4883,"matches":57,"player_id":251527103},{"rank":227,"player_name":"Jovann","rank_name":"Celestial 2","score":4883,"matches":133,"player_id":1860885445},{"rank":228,"player_name":"Eham","rank_name":"Celestial 2","score":4881,"matches":126,"player_id":986106947},{"rank":229,"player_name":"freekuu","rank_name":"Celestial 3","score":4881,"matches":109,"player_id":785442835},{"rank":230,"player_name":"DaddySeahorse","rank_name":"Celestial 3","score":4880,"matches":84,"player_id":518943339},{"rank":231,"player_name":"monstrixx","rank_name":"Celestial 3","score":4879,"matches":98,"player_id":270647088},{"rank":232,"player_name":"Sell A Door","rank_name":"Celestial 3","score":4879,"matches":53,"player_id":1854314465},{"rank":233,"player_name":"paBl0s","rank_name":"Celestial 2","score":4879,"matches":206,"player_id":175789697},{"rank":234,"player_name":"JayTurtle","rank_name":"Celestial 2","score":4879,"matches":152,"player_id":1849356222},{"rank":235,"player_name":"Paranоia","rank_name":"Celestial 3","score":4877,"matches":391,"player_id":2141632387},{"rank":236,"player_name":"camerhn","rank_name":"Celestial 2","score":4873,"matches":80,"player_id":1772796103},{"rank":237,"player_name":"z1unknown","rank_name":"Celestial 2","score":4872,"matches":69,"player_id":200996980},{"rank":238,"player_name":"SpeedyCSGOggTV","rank_name":"Celestial 2","score":4872,"matches":205,"player_id":1290732194},{"rank":239,"player_name":"beats her guts","rank_name":"Celestial 2","score":4870,"matches":61,"player_id":946381874},{"rank":240,"player_name":"AloneYZ_","rank_name":"Celestial 3","score":4870,"matches":139,"player_id":2057606687},{"rank":241,"player_name":"Suneri","rank_name":"Celestial 3","score":4869,"matches":66,"player_id":22833437},{"rank":242,"player_name":"Branchies","rank_name":"Celestial 3","score":4867,"matches":74,"player_id":1673285057},{"rank":243,"player_name":"Crows'eye","rank_name":"Celestial 3","score":4865,"matches":75,"player_id":355582313},{"rank":244,"player_name":"tecao","rank_name":"Celestial 3","score":4865,"matches":64,"player_id":633235550},{"rank":245,"player_name":"GirthatronZB","rank_name":"Celestial 3","score":4865,"matches":129,"player_id":1072104200},{"rank":246,"player_name":"rodjzg","rank_name":"Celestial 3","score":4864,"matches":132,"player_id":295960695},{"rank":247,"player_name":"Maquiaa","rank_name":"Celestial 3","score":4863,"matches":157,"player_id":1992608236},{"rank":248,"player_name":"nuts1234","rank_name":"Celestial 3","score":4863,"matches":57,"player_id":153852547},{"rank":249,"player_name":"FǕŖȐŶFĔMƁǾY","rank_name":"Celestial 3","score":4863,"matches":54,"player_id":1117057280},{"rank":250,"player_name":"realartax","rank_name":"Celestial 3","score":4861,"matches":135,"player_id":83259118},{"rank":251,"player_name":"WhoppenOppen","rank_name":"Celestial 3","score":4861,"matches":97,"player_id":1740100917},{"rank":252,"player_name":"xMako","rank_name":"Celestial 3","score":4860,"matches":151,"player_id":899492740},{"rank":253,"player_name":"toblerone784","rank_name":"Celestial 3","score":4853,"matches":89,"player_id":635673778},{"rank":254,"player_name":"Soroxsi","rank_name":"Celestial 3","score":4853,"matches":58,"player_id":848960365},{"rank":255,"player_name":"jriz","rank_name":"Celestial 3","score":4853,"matches":219,"player_id":1422573158},{"rank":256,"player_name":"DedShotDyl24","rank_name":"Celestial 3","score":4851,"matches":71,"player_id":937200645},{"rank":257,"player_name":"-LunaticSam-YT","rank_name":"Celestial 3","score":4851,"matches":55,"player_id":1138906818},{"rank":258,"player_name":"Guitar_OW","rank_name":"Celestial 3","score":4850,"matches":210,"player_id":1103298059},{"rank":259,"player_name":"Neisan","rank_name":"Celestial 3","score":4850,"matches":54,"player_id":19779603},{"rank":260,"player_name":"Nyw","rank_name":"Celestial 3","score":4848,"matches":53,"player_id":280862789},{"rank":261,"player_name":"Quadrilingual","rank_name":"Celestial 3","score":4848,"matches":61,"player_id":1919704246},{"rank":262,"player_name":"1000Bluntѕ","rank_name":"Celestial 3","score":4847,"matches":125,"player_id":714985567},{"rank":263,"player_name":"Aligg","rank_name":"Celestial 3","score":4846,"matches":86,"player_id":1554192873},{"rank":264,"player_name":"sqwamper","rank_name":"Celestial 3","score":4845,"matches":92,"player_id":1724661795},{"rank":265,"player_name":"Lezlinos","rank_name":"Celestial 3","score":4845,"matches":102,"player_id":342814168},{"rank":266,"player_name":"Scorpion_e_bow","rank_name":"Celestial 3","score":4845,"matches":117,"player_id":691260790},{"rank":267,"player_name":"Bruhmomen2314","rank_name":"Celestial 3","score":4845,"matches":58,"player_id":1171843365},{"rank":268,"player_name":"Azarath'","rank_name":"Celestial 3","score":4845,"matches":82,"player_id":177651776},{"rank":269,"player_name":"m2ro","rank_name":"Celestial 3","score":4843,"matches":51,"player_id":584955295},{"rank":270,"player_name":"niko 172","rank_name":"Celestial 3","score":4843,"matches":178,"player_id":1184590848},{"rank":271,"player_name":"WORST ULTS NA","rank_name":"Celestial 3","score":4843,"matches":58,"player_id":406914549},{"rank":272,"player_name":"M1lanoTTV","rank_name":"Celestial 3","score":4843,"matches":211,"player_id":672848639},{"rank":273,"player_name":".S.E.A.","rank_name":"Celestial 3","score":4842,"matches":66,"player_id":1214753207},{"rank":274,"player_name":"Joséph","rank_name":"Celestial 3","score":4840,"matches":125,"player_id":620925146},{"rank":275,"player_name":"cfv.","rank_name":"Celestial 3","score":4840,"matches":72,"player_id":1446355644},{"rank":276,"player_name":"Partychat","rank_name":"Celestial 3","score":4838,"matches":73,"player_id":2083104976},{"rank":277,"player_name":"tuRkkz","rank_name":"Celestial 3","score":4837,"matches":78,"player_id":510619339},{"rank":278,"player_name":"Prairie-","rank_name":"Celestial 3","score":4836,"matches":109,"player_id":334950982},{"rank":279,"player_name":"huterxx","rank_name":"Celestial 3","score":4835,"matches":77,"player_id":1526358680},{"rank":280,"player_name":"demonbabar","rank_name":"Celestial 3","score":4834,"matches":52,"player_id":1198220715},{"rank":281,"player_name":"AuraOverload.","rank_name":"Celestial 3","score":4833,"matches":54,"player_id":1964342009},{"rank":282,"player_name":"GeeGEZ","rank_name":"Celestial 3","score":4832,"matches":53,"player_id":353215802},{"rank":283,"player_name":"Vooshii","rank_name":"Celestial 3","score":4832,"matches":59,"player_id":453106201},{"rank":284,"player_name":"cuthe","rank_name":"Celestial 3","score":4832,"matches":63,"player_id":1415244219},{"rank":285,"player_name":"Jablinsquin","rank_name":"Celestial 3","score":4830,"matches":54,"player_id":198753716},{"rank":286,"player_name":"ezkyz","rank_name":"Celestial 3","score":4830,"matches":106,"player_id":1490082699},{"rank":287,"player_name":"IIChris","rank_name":"Celestial 3","score":4828,"matches":85,"player_id":1256934425},{"rank":288,"player_name":"OGJACK","rank_name":"Celestial 3","score":4827,"matches":148,"player_id":600618988},{"rank":289,"player_name":"azzaamenk","rank_name":"Celestial 3","score":4827,"matches":488,"player_id":1568652577},{"rank":290,"player_name":"cellecular","rank_name":"Celestial 3","score":4824,"matches":109,"player_id":878158993},{"rank":291,"player_name":"9874414ZZZZ","rank_name":"Celestial 3","score":4824,"matches":80,"player_id":1775540657},{"rank":292,"player_name":"matixinho","rank_name":"Celestial 3","score":4824,"matches":60,"player_id":1694562804},{"rank":293,"player_name":"roked","rank_name":"Celestial 3","score":4824,"matches":133,"player_id":1225075256},{"rank":294,"player_name":"neuok","rank_name":"Celestial 3","score":4823,"matches":58,"player_id":1004997476},{"rank":295,"player_name":"Seiichirouu","rank_name":"Celestial 3","score":4823,"matches":62,"player_id":951056107},{"rank":296,"player_name":"Airendercraft","rank_name":"Celestial 3","score":4822,"matches":165,"player_id":1192190814},{"rank":297,"player_name":"WidowProBroLOL","rank_name":"Celestial 3","score":4822,"matches":77,"player_id":365493466},{"rank":298,"player_name":"9wke","rank_name":"Celestial 3","score":4821,"matches":89,"player_id":1783532136},{"rank":299,"player_name":"ᵐᵉ","rank_name":"Celestial 3","score":4821,"matches":55,"player_id":342342846},{"rank":300,"player_name":"TheAstartes","rank_name":"Celestial 3","score":4820,"matches":117,"player_id":57270688},{"rank":301,"player_name":"hansy.","rank_name":"Celestial 3","score":4819,"matches":74,"player_id":506895679},{"rank":302,"player_name":"xDreaded","rank_name":"Celestial 3","score":4818,"matches":64,"player_id":945316094},{"rank":303,"player_name":"Z Q H","rank_name":"Celestial 3","score":4818,"matches":76,"player_id":1177667839},{"rank":304,"player_name":"Darkin774","rank_name":"Celestial 3","score":4818,"matches":62,"player_id":859099484},{"rank":305,"player_name":"dae067","rank_name":"Celestial 3","score":4818,"matches":68,"player_id":88569763},{"rank":306,"player_name":"Non0","rank_name":"Celestial 3","score":4818,"matches":51,"player_id":453631711},{"rank":307,"player_name":"viper room","rank_name":"Celestial 3","score":4817,"matches":173,"player_id":991946195},{"rank":308,"player_name":"HniM63","rank_name":"Celestial 3","score":4817,"matches":112,"player_id":865577230},{"rank":309,"player_name":"Kitsukii","rank_name":"Celestial 3","score":4816,"matches":75,"player_id":1766502605},{"rank":310,"player_name":"clone hero","rank_name":"Celestial 3","score":4816,"matches":199,"player_id":764593943},{"rank":311,"player_name":"Sencrz","rank_name":"Celestial 3","score":4816,"matches":117,"player_id":1532505684},{"rank":312,"player_name":"DeaDArham25","rank_name":"Celestial 3","score":4815,"matches":219,"player_id":1949146018},{"rank":313,"player_name":"rockaror","rank_name":"Celestial 3","score":4815,"matches":107,"player_id":1138738882},{"rank":314,"player_name":"rdpaco","rank_name":"Celestial 3","score":4815,"matches":99,"player_id":336046085},{"rank":315,"player_name":"evoooo0","rank_name":"Celestial 3","score":4814,"matches":161,"player_id":171781744},{"rank":316,"player_name":"bw21","rank_name":"Celestial 3","score":4814,"matches":158,"player_id":809406992},{"rank":317,"player_name":"realdaddysaif","rank_name":"Celestial 3","score":4814,"matches":124,"player_id":493784396},{"rank":318,"player_name":"Suwoo","rank_name":"Celestial 3","score":4813,"matches":94,"player_id":20910175},{"rank":319,"player_name":"Nitro_DeNyxx","rank_name":"Celestial 3","score":4812,"matches":86,"player_id":1278669762},{"rank":320,"player_name":"RoyalRezz","rank_name":"Celestial 3","score":4812,"matches":242,"player_id":363994559},{"rank":321,"player_name":"Johnson .","rank_name":"Celestial 3","score":4812,"matches":108,"player_id":1107510716},{"rank":322,"player_name":"YungSweat","rank_name":"Celestial 3","score":4812,"matches":429,"player_id":1605277258},{"rank":323,"player_name":"EasyFTW","rank_name":"Celestial 3","score":4812,"matches":135,"player_id":250093327},{"rank":324,"player_name":"rukiafeetpic","rank_name":"Celestial 3","score":4811,"matches":131,"player_id":101101982},{"rank":325,"player_name":"getojojoe","rank_name":"Celestial 3","score":4811,"matches":236,"player_id":150761076},{"rank":326,"player_name":"MefSZN","rank_name":"Celestial 3","score":4811,"matches":59,"player_id":862489700},{"rank":327,"player_name":"ameth_sama","rank_name":"Celestial 3","score":4810,"matches":96,"player_id":2053530659},{"rank":328,"player_name":"buttsexy","rank_name":"Celestial 3","score":4809,"matches":53,"player_id":30813138},{"rank":329,"player_name":"Erjohn","rank_name":"Celestial 3","score":4808,"matches":147,"player_id":1237824124},{"rank":330,"player_name":"Preds parlay","rank_name":"Celestial 3","score":4808,"matches":119,"player_id":1911313939},{"rank":331,"player_name":"Spheaf","rank_name":"Celestial 3","score":4808,"matches":61,"player_id":1051188511},{"rank":332,"player_name":"sinister.-","rank_name":"Celestial 3","score":4807,"matches":150,"player_id":493307199},{"rank":333,"player_name":"1Cream GGEZ","rank_name":"Celestial 3","score":4806,"matches":112,"player_id":932539653},{"rank":334,"player_name":"9InchStarlord","rank_name":"Celestial 3","score":4806,"matches":219,"player_id":476082981},{"rank":335,"player_name":"Rafoshark","rank_name":"Celestial 3","score":4806,"matches":53,"player_id":1846976648},{"rank":336,"player_name":"Goophed","rank_name":"Celestial 3","score":4805,"matches":57,"player_id":2129659088},{"rank":337,"player_name":"itzsilenthilll","rank_name":"Celestial 3","score":4805,"matches":83,"player_id":403255941},{"rank":338,"player_name":"Nyan","rank_name":"Celestial 3","score":4805,"matches":57,"player_id":967917322},{"rank":339,"player_name":"lionking","rank_name":"Celestial 3","score":4805,"matches":55,"player_id":1282308981},{"rank":340,"player_name":"womelet","rank_name":"Celestial 3","score":4805,"matches":122,"player_id":1786792480},{"rank":341,"player_name":"huhuhuhuhul","rank_name":"Celestial 3","score":4804,"matches":70,"player_id":1392183465},{"rank":342,"player_name":"TabakTobi","rank_name":"Celestial 3","score":4804,"matches":112,"player_id":1756143028},{"rank":343,"player_name":"FLOCK KILLER","rank_name":"Celestial 3","score":4803,"matches":375,"player_id":364472179},{"rank":344,"player_name":"Gortissimo","rank_name":"Celestial 3","score":4803,"matches":51,"player_id":857516942},{"rank":345,"player_name":"juju fps","rank_name":"Celestial 3","score":4803,"matches":52,"player_id":1355541506},{"rank":346,"player_name":"cosmiccc","rank_name":"Celestial 3","score":4802,"matches":85,"player_id":1056794300},{"rank":347,"player_name":"jayvysh","rank_name":"Celestial 3","score":4802,"matches":114,"player_id":470355569},{"rank":348,"player_name":"R3WOP","rank_name":"Celestial 3","score":4802,"matches":86,"player_id":1102634001},{"rank":349,"player_name":"Kiyo .-.","rank_name":"Celestial 3","score":4801,"matches":105,"player_id":1038021416},{"rank":350,"player_name":"AntiTerrorism","rank_name":"Celestial 3","score":4801,"matches":635,"player_id":1791693043},{"rank":351,"player_name":"Pajama Jim","rank_name":"Celestial 3","score":4801,"matches":64,"player_id":1634085580},{"rank":352,"player_name":"Prisky","rank_name":"Celestial 3","score":4801,"matches":57,"player_id":2106038468},{"rank":353,"player_name":"SatireG7","rank_name":"Celestial 3","score":4801,"matches":70,"player_id":1619256379},{"rank":354,"player_name":"mohaanad","rank_name":"Celestial 3","score":4801,"matches":133,"player_id":1489764603},{"rank":355,"player_name":"GraciaSKIBIDI.","rank_name":"Celestial 3","score":4800,"matches":163,"player_id":1748296068},{"rank":356,"player_name":"Cupcake777","rank_name":"Celestial 3","score":4800,"matches":156,"player_id":578371433},{"rank":357,"player_name":"Drazytox","rank_name":"Celestial 3","score":4800,"matches":69,"player_id":1517698552},{"rank":358,"player_name":"Micerule4","rank_name":"Celestial 3","score":4799,"matches":94,"player_id":977836515},{"rank":359,"player_name":"ivanovrolls","rank_name":"Celestial 3","score":4799,"matches":60,"player_id":1353339606},{"rank":360,"player_name":"Toward","rank_name":"Celestial 3","score":4797,"matches":54,"player_id":1373449882},{"rank":361,"player_name":"mehtric.","rank_name":"Celestial 3","score":4797,"matches":81,"player_id":1826986777},{"rank":362,"player_name":"hanbisse","rank_name":"Grandmaster 1","score":4797,"matches":108,"player_id":1149657006},{"rank":363,"player_name":"Loveey","rank_name":"Celestial 3","score":4797,"matches":83,"player_id":27300103},{"rank":364,"player_name":"MilleDidrik","rank_name":"Celestial 3","score":4796,"matches":57,"player_id":1691024204},{"rank":365,"player_name":"descerlaprabc2","rank_name":"Celestial 3","score":4795,"matches":83,"player_id":37926071},{"rank":366,"player_name":"Zoo.M80","rank_name":"Celestial 3","score":4791,"matches":52,"player_id":93082721},{"rank":367,"player_name":"PrimeH0pe","rank_name":"Celestial 3","score":4790,"matches":263,"player_id":1421870257},{"rank":368,"player_name":"MgClutch","rank_name":"Grandmaster 1","score":4790,"matches":252,"player_id":1061092028},{"rank":369,"player_name":"TTV Dxlict","rank_name":"Celestial 3","score":4789,"matches":127,"player_id":739329276},{"rank":370,"player_name":"w o p","rank_name":"Grandmaster 1","score":4789,"matches":68,"player_id":456469682},{"rank":371,"player_name":"Xito_","rank_name":"Celestial 3","score":4787,"matches":92,"player_id":2104081455},{"rank":372,"player_name":"outflashed","rank_name":"Celestial 3","score":4787,"matches":53,"player_id":1129128251},{"rank":373,"player_name":"PRODval","rank_name":"Celestial 3","score":4786,"matches":56,"player_id":1314076408},{"rank":374,"player_name":"sneezwtf","rank_name":"Grandmaster 1","score":4786,"matches":257,"player_id":715679598},{"rank":375,"player_name":"Tetrow","rank_name":"Celestial 3","score":4786,"matches":75,"player_id":1173455585},{"rank":376,"player_name":"SoyPanxD","rank_name":"Grandmaster 1","score":4786,"matches":97,"player_id":962998924},{"rank":377,"player_name":"BeepImtheJeep","rank_name":"Celestial 3","score":4784,"matches":53,"player_id":1608597893},{"rank":378,"player_name":"prezay","rank_name":"Grandmaster 1","score":4784,"matches":205,"player_id":888446144},{"rank":379,"player_name":"Luxri","rank_name":"Celestial 3","score":4784,"matches":76,"player_id":1605928257},{"rank":380,"player_name":"Captivated_","rank_name":"Celestial 3","score":4783,"matches":75,"player_id":735823724},{"rank":381,"player_name":"hi im rob","rank_name":"Celestial 3","score":4783,"matches":53,"player_id":201007114},{"rank":382,"player_name":"Bu8","rank_name":"Celestial 3","score":4781,"matches":67,"player_id":1861418138},{"rank":383,"player_name":"neoccc","rank_name":"Celestial 3","score":4780,"matches":145,"player_id":1942686423},{"rank":384,"player_name":"Marthy","rank_name":"Grandmaster 1","score":4780,"matches":94,"player_id":2142420181},{"rank":385,"player_name":"Timph","rank_name":"Celestial 3","score":4779,"matches":51,"player_id":614813425},{"rank":386,"player_name":"Chauw","rank_name":"Grandmaster 1","score":4779,"matches":60,"player_id":469974140},{"rank":387,"player_name":"Retosao","rank_name":"Grandmaster 1","score":4777,"matches":76,"player_id":2111673927},{"rank":388,"player_name":"김탤","rank_name":"Grandmaster 1","score":4777,"matches":51,"player_id":1606085872},{"rank":389,"player_name":"LegitDio","rank_name":"Celestial 3","score":4777,"matches":153,"player_id":1261751113},{"rank":390,"player_name":"YTUnknownPlays","rank_name":"Grandmaster 1","score":4776,"matches":94,"player_id":797494144},{"rank":391,"player_name":"Lagazy","rank_name":"Celestial 3","score":4775,"matches":66,"player_id":136111791},{"rank":392,"player_name":"_Jab_","rank_name":"Grandmaster 1","score":4772,"matches":206,"player_id":321501269},{"rank":393,"player_name":"ジー","rank_name":"Celestial 3","score":4771,"matches":198,"player_id":678829999},{"rank":394,"player_name":"charmony dove","rank_name":"Celestial 3","score":4770,"matches":133,"player_id":2054044251},{"rank":395,"player_name":"_Statiic","rank_name":"Grandmaster 1","score":4770,"matches":135,"player_id":1063070271},{"rank":396,"player_name":"Demonicbuthole","rank_name":"Grandmaster 1","score":4766,"matches":59,"player_id":134644538},{"rank":397,"player_name":"nuny on twitch","rank_name":"Grandmaster 1","score":4766,"matches":75,"player_id":60731179},{"rank":398,"player_name":"RiverCreature2","rank_name":"Grandmaster 1","score":4765,"matches":115,"player_id":1517917341},{"rank":399,"player_name":"Rubenzx","rank_name":"Grandmaster 1","score":4765,"matches":194,"player_id":862411989},{"rank":400,"player_name":"harlemia","rank_name":"Grandmaster 1","score":4765,"matches":118,"player_id":945546004},{"rank":401,"player_name":"MGSL","rank_name":"Grandmaster 1","score":4763,"matches":260,"player_id":1426454849},{"rank":402,"player_name":"juliop12","rank_name":"Grandmaster 1","score":4763,"matches":299,"player_id":123128194},{"rank":403,"player_name":"synchrony","rank_name":"Grandmaster 1","score":4763,"matches":92,"player_id":181309460},{"rank":404,"player_name":"Un0Koa","rank_name":"Grandmaster 1","score":4763,"matches":73,"player_id":133782526},{"rank":405,"player_name":"iColt","rank_name":"Grandmaster 1","score":4762,"matches":52,"player_id":303773796},{"rank":406,"player_name":"Triizhy","rank_name":"Grandmaster 1","score":4760,"matches":71,"player_id":91123448},{"rank":407,"player_name":"OW2ISPEAK","rank_name":"Grandmaster 1","score":4759,"matches":99,"player_id":1489209862},{"rank":408,"player_name":"WABY DON HEARN","rank_name":"Grandmaster 1","score":4759,"matches":116,"player_id":1516297482},{"rank":409,"player_name":"magiks vibrato","rank_name":"Grandmaster 1","score":4758,"matches":158,"player_id":134325927},{"rank":410,"player_name":"Ohiomogger","rank_name":"Grandmaster 1","score":4758,"matches":200,"player_id":1895732467},{"rank":411,"player_name":"Aka_Asf4lto","rank_name":"Grandmaster 1","score":4755,"matches":130,"player_id":285168300},{"rank":412,"player_name":"Kibzu","rank_name":"Grandmaster 1","score":4753,"matches":62,"player_id":708924728},{"rank":413,"player_name":"Braizo","rank_name":"Grandmaster 1","score":4753,"matches":88,"player_id":58068966},{"rank":414,"player_name":"JuicedKevin","rank_name":"Grandmaster 1","score":4753,"matches":118,"player_id":2112319980},{"rank":415,"player_name":"A1thur","rank_name":"Grandmaster 1","score":4752,"matches":85,"player_id":1259281199},{"rank":416,"player_name":"M115","rank_name":"Grandmaster 1","score":4752,"matches":156,"player_id":637948555},{"rank":417,"player_name":"Kazerio69","rank_name":"Grandmaster 1","score":4751,"matches":54,"player_id":1099054504},{"rank":418,"player_name":"MaceFPS","rank_name":"Grandmaster 1","score":4751,"matches":68,"player_id":519549500},{"rank":419,"player_name":"Free L","rank_name":"Grandmaster 1","score":4750,"matches":56,"player_id":979720638},{"rank":420,"player_name":"Aldebaran アル","rank_name":"Grandmaster 1","score":4750,"matches":349,"player_id":1228949607},{"rank":421,"player_name":"L2KxD","rank_name":"Grandmaster 1","score":4749,"matches":61,"player_id":851399060},{"rank":422,"player_name":"7kar2","rank_name":"Grandmaster 1","score":4748,"matches":64,"player_id":67095542},{"rank":423,"player_name":"f1reee","rank_name":"Grandmaster 1","score":4748,"matches":67,"player_id":710653461},{"rank":424,"player_name":"xtrn","rank_name":"Grandmaster 1","score":4745,"matches":79,"player_id":1118901947},{"rank":425,"player_name":"Sabiito","rank_name":"Grandmaster 1","score":4744,"matches":54,"player_id":1311897306},{"rank":426,"player_name":"Hindbærsnitter","rank_name":"Grandmaster 1","score":4742,"matches":106,"player_id":1170790797},{"rank":427,"player_name":"Konobie","rank_name":"Grandmaster 1","score":4742,"matches":127,"player_id":1001753790},{"rank":428,"player_name":"DarkLordGyat69","rank_name":"Grandmaster 1","score":4741,"matches":122,"player_id":934460143},{"rank":429,"player_name":"vudoaan","rank_name":"Grandmaster 1","score":4740,"matches":167,"player_id":1593003071},{"rank":430,"player_name":"KalabJab","rank_name":"Grandmaster 1","score":4740,"matches":51,"player_id":1893540837},{"rank":431,"player_name":"maxential","rank_name":"Grandmaster 1","score":4740,"matches":195,"player_id":975012663},{"rank":432,"player_name":"WaveK1ng","rank_name":"Grandmaster 1","score":4737,"matches":163,"player_id":973612664},{"rank":433,"player_name":"Nico1tap","rank_name":"Grandmaster 1","score":4737,"matches":58,"player_id":688021747},{"rank":434,"player_name":"dragun1","rank_name":"Grandmaster 1","score":4736,"matches":74,"player_id":521075559},{"rank":435,"player_name":"Benshi-XD","rank_name":"Grandmaster 1","score":4736,"matches":315,"player_id":1959233177},{"rank":436,"player_name":"ARTORIAX","rank_name":"Grandmaster 1","score":4736,"matches":171,"player_id":1680664195},{"rank":437,"player_name":"Faircl0ut","rank_name":"Grandmaster 1","score":4735,"matches":59,"player_id":2057896785},{"rank":438,"player_name":"진정된","rank_name":"Grandmaster 1","score":4735,"matches":216,"player_id":1101828657},{"rank":439,"player_name":"lowdiddler","rank_name":"Grandmaster 1","score":4734,"matches":135,"player_id":222502459},{"rank":440,"player_name":"meeebro","rank_name":"Grandmaster 1","score":4734,"matches":97,"player_id":1702818598},{"rank":441,"player_name":"TTVMagicMario","rank_name":"Grandmaster 1","score":4734,"matches":418,"player_id":1259892716},{"rank":442,"player_name":"AnotherHero","rank_name":"Grandmaster 1","score":4733,"matches":91,"player_id":167461894},{"rank":443,"player_name":"IAmGuavaFruit","rank_name":"Grandmaster 1","score":4733,"matches":87,"player_id":298891014},{"rank":444,"player_name":"EMinor","rank_name":"Grandmaster 1","score":4732,"matches":64,"player_id":1415277170},{"rank":445,"player_name":"Maple.YT","rank_name":"Grandmaster 1","score":4732,"matches":91,"player_id":1398461680},{"rank":446,"player_name":"5kll","rank_name":"Grandmaster 1","score":4730,"matches":150,"player_id":338729702},{"rank":447,"player_name":"jheesh","rank_name":"Grandmaster 1","score":4728,"matches":74,"player_id":1064879544},{"rank":448,"player_name":"FadesLie","rank_name":"Grandmaster 1","score":4727,"matches":91,"player_id":875766734},{"rank":449,"player_name":"этот пирог","rank_name":"Grandmaster 1","score":4727,"matches":51,"player_id":902461989},{"rank":450,"player_name":"LBeastly","rank_name":"Grandmaster 1","score":4726,"matches":110,"player_id":2118153758},{"rank":451,"player_name":"cravings.","rank_name":"Grandmaster 1","score":4724,"matches":105,"player_id":250764009},{"rank":452,"player_name":"btw","rank_name":"Grandmaster 1","score":4724,"matches":80,"player_id":547759527},{"rank":453,"player_name":"PhDInWar","rank_name":"Grandmaster 1","score":4723,"matches":52,"player_id":1195437226},{"rank":454,"player_name":"HawkTuaTaper45","rank_name":"Grandmaster 1","score":4722,"matches":109,"player_id":26097748},{"rank":455,"player_name":"TTV MeDicinaal","rank_name":"Grandmaster 1","score":4722,"matches":186,"player_id":1177769670},{"rank":456,"player_name":"-mirin","rank_name":"Grandmaster 1","score":4722,"matches":114,"player_id":27450089},{"rank":457,"player_name":"Parad1gm","rank_name":"Grandmaster 1","score":4721,"matches":58,"player_id":1546309307},{"rank":458,"player_name":"Nachingui","rank_name":"Grandmaster 1","score":4720,"matches":142,"player_id":313962866},{"rank":459,"player_name":"submer","rank_name":"Grandmaster 1","score":4720,"matches":194,"player_id":53403284},{"rank":460,"player_name":"exodius893","rank_name":"Grandmaster 1","score":4719,"matches":64,"player_id":929676662},{"rank":461,"player_name":"clemstas","rank_name":"Grandmaster 1","score":4718,"matches":225,"player_id":1096609207},{"rank":462,"player_name":"Frostics","rank_name":"Grandmaster 1","score":4717,"matches":260,"player_id":1394964524},{"rank":463,"player_name":"Abstract Thot","rank_name":"Grandmaster 1","score":4717,"matches":63,"player_id":1768392058},{"rank":464,"player_name":"Pezunas","rank_name":"Grandmaster 1","score":4716,"matches":178,"player_id":35591805},{"rank":465,"player_name":"ilestfallenb0y","rank_name":"Grandmaster 1","score":4716,"matches":318,"player_id":1569978934},{"rank":466,"player_name":"Kengggggg","rank_name":"Grandmaster 1","score":4715,"matches":87,"player_id":1421604899},{"rank":467,"player_name":"CouldBeDead","rank_name":"Grandmaster 1","score":4714,"matches":185,"player_id":85710926},{"rank":468,"player_name":"Panck3s","rank_name":"Grandmaster 1","score":4714,"matches":87,"player_id":374868940},{"rank":469,"player_name":"lcias","rank_name":"Grandmaster 1","score":4714,"matches":53,"player_id":1897734605},{"rank":470,"player_name":"nyyle","rank_name":"Grandmaster 1","score":4714,"matches":89,"player_id":2012356701},{"rank":471,"player_name":"DinglousRukia","rank_name":"Grandmaster 1","score":4712,"matches":89,"player_id":645212224},{"rank":472,"player_name":"Guts.","rank_name":"Grandmaster 1","score":4712,"matches":78,"player_id":2002423875},{"rank":473,"player_name":"Zеvs","rank_name":"Grandmaster 1","score":4711,"matches":96,"player_id":763017208},{"rank":474,"player_name":"-LowQuality-","rank_name":"Grandmaster 1","score":4710,"matches":255,"player_id":992955662},{"rank":475,"player_name":"4strx","rank_name":"Grandmaster 1","score":4709,"matches":102,"player_id":416889509},{"rank":476,"player_name":"rainebrr","rank_name":"Grandmaster 1","score":4708,"matches":76,"player_id":507170907},{"rank":477,"player_name":"AsianHernandez","rank_name":"Grandmaster 1","score":4707,"matches":89,"player_id":1333345019},{"rank":478,"player_name":"Chuckmao","rank_name":"Grandmaster 1","score":4707,"matches":75,"player_id":1603591061},{"rank":479,"player_name":"Twz21","rank_name":"Grandmaster 1","score":4706,"matches":74,"player_id":576054609},{"rank":480,"player_name":"SubduedOrb","rank_name":"Grandmaster 1","score":4706,"matches":82,"player_id":796466515},{"rank":481,"player_name":"codufrog","rank_name":"Grandmaster 1","score":4706,"matches":68,"player_id":49011202},{"rank":482,"player_name":"Rene","rank_name":"Grandmaster 1","score":4705,"matches":280,"player_id":700195404},{"rank":483,"player_name":"ALSHMRANI","rank_name":"Grandmaster 1","score":4705,"matches":78,"player_id":1468071813},{"rank":484,"player_name":"2Leaky","rank_name":"Grandmaster 1","score":4704,"matches":106,"player_id":1843258440},{"rank":485,"player_name":"Unsurface","rank_name":"Grandmaster 1","score":4704,"matches":100,"player_id":92088288},{"rank":486,"player_name":"FakeTaxiDriver","rank_name":"Grandmaster 1","score":4704,"matches":61,"player_id":206400723},{"rank":487,"player_name":"exceptive","rank_name":"Grandmaster 1","score":4704,"matches":61,"player_id":1775493574},{"rank":488,"player_name":"Rossovitch","rank_name":"Grandmaster 1","score":4704,"matches":73,"player_id":1960741227},{"rank":489,"player_name":"Follows","rank_name":"Grandmaster 1","score":4704,"matches":73,"player_id":1200643877},{"rank":490,"player_name":"Saulmonella","rank_name":"Grandmaster 1","score":4703,"matches":75,"player_id":491495403},{"rank":491,"player_name":"Tohhka","rank_name":"Grandmaster 1","score":4703,"matches":80,"player_id":791413402},{"rank":492,"player_name":"KimMinjiLuva","rank_name":"Grandmaster 1","score":4702,"matches":88,"player_id":1320763871},{"rank":493,"player_name":"TARSxD","rank_name":"Grandmaster 1","score":4702,"matches":118,"player_id":807263296},{"rank":494,"player_name":"theblueninja10","rank_name":"Grandmaster 1","score":4702,"matches":117,"player_id":1099867049},{"rank":495,"player_name":"Pearcer","rank_name":"Grandmaster 1","score":4702,"matches":60,"player_id":1789412906},{"rank":496,"player_name":"YT--LunaticSam","rank_name":"Grandmaster 1","score":4700,"matches":120,"player_id":1837996292},{"rank":497,"player_name":"BUFFEN","rank_name":"Grandmaster 2","score":4699,"matches":86,"player_id":133838146},{"rank":498,"player_name":"Verizionn","rank_name":"Grandmaster 2","score":4698,"matches":332,"player_id":1929981806},{"rank":499,"player_name":"Grůb","rank_name":"Grandmaster 2","score":4698,"matches":59,"player_id":1432159381},{"rank":500,"player_name":"Ghostmaster","rank_name":"Grandmaster 2","score":4698,"matches":105,"player_id":1540196585}]